Workbook

Sheet Translators_MT_Data
A1: Covidence # | B1: Study ID_1 | C1: Study ID | D1: Title | E1: Lead author contact details | F1: Lead author affiliation | G1: Lead author affiliation country | H1: Publication date | I1: Publication Year | J1: Country in which the study was conducted | K1: Aim of study | L1: Type of study Questionnaire | M1: Type of study Focus Group | N1: Type of study Interview | O1: Type of study Other | P1: Closed Number of questions | Q1: Open Number of questions | R1: Total Number of questions | S1: Start date | T1: End date | U1: Method of dissemination | V1: Method of participation Online | W1: Method of participation Offline | X1: Study funding sources | Y1: Population description | Z1: Different population | AA1: Translation Area | AB1: Total number of participants | AC1: Detailed number of participants | AD1: Main results | AE1: Main conclusions | AF1: Key Terminology in Conclusions | AG1: Categories focused | AH1: Adoption (AD) > AD_High | AI1: Adoption (AD) > AD_Moderate | AJ1: Adoption (AD) > AD_Low | AK1: Adoption (AD) > AD_None | AL1: Attitude (ATT) > ATT_Negative | AM1: Attitude (ATT) > ATT_Positive | AN1: Ethical Concerns (EC) > EC_Bias | AO1: Ethical Concerns (EC) > EC_Copyright | AP1: Ethical Concerns (EC) > EC_Data safety & confidentiality | AQ1: Ethical Concerns (EC) > EC_Environmental sustainability | AR1: Ethical Concerns (EC) > EC_Payment | AS1: Ethical Concerns (EC) > EC_Quality | AT1: Ethical Concerns (EC) > EC_Translators’ role & status | AU1: Ethical Concerns (EC) > EC_Other | AV1: Literacy (LIT) > LIT_Generic | AW1: Literacy (LIT) > LIT_None | AX1: Literacy (LIT) > LIT_Low | AY1: Literacy (LIT) > LIT_High
A2: 76 | B2: 2CNYZQB7 | C2: Nzuanke 2018 | D2: Knowledge and Use of Computer-Assisted Translation Tools on Professional Translation in Nigeria | E2: Samson Fabian Nzuanke | F2: University of Calabar, Calabar-Nigeria | G2: Nigeria | H2: 2018/01 | I2: =LEFT(SLR_Covidence_Data_Extraction__66_files[[#This Row],[Publication date]],4) -> 2018 | J2: Nigeria | K2: To analyse the awareness level of professional Nigerian translators regarding state-of-the-art translation technologies - specifically Computer-Assisted Translation (CAT) tools like translation memory (TM), voice recognition, and term-base management. | L2: Questionnaire | S2: 2016/10 | T2: 2017/06 | U2: Social media; Professional associations networks; Other: ECOWAS Commission | V2: Online | Y2: Professional translators | Z2: Professional translators | AA2: General | AB2: 80 | AC2: 80 | AD2: 1. The Technology Usage Gap The data shows a stark contrast between "traditional" digital tools and specialized translation software: • Universal Tools: 100% of respondents use Microsoft Word and electronic dictionaries/glossaries. • Persistent Traditionalism: 60% of translators still rely on hard-copy dictionaries and pen and paper for their professional work. • Low CAT Adoption: Only 30% of translators use CAT tools generally. Specifically, only 20% use Translation Memory (TM) and only 10% use terminology management software. • Complete Absence: 0% of respondents utilized voice recognition or Optical Character Recognition (OCR) tools. 2. Awareness and Misconceptions A primary finding was that many translators do not understand the nature of the tools available to them: • The MT vs. TM Confusion: 50% of Nigerian translators mistakenly believe that Translation Memory is the same as Machine Translation (automatic translation without human aid). The researchers note this misconception directly hinders tool acquisition because translators view the tools as "not useful" or "unreliable". • Educational Shortfall: Although 70% of respondents indicated that CAT tools existed during their professional training, only 40% were actually taught how to use them in school. This suggests that academic curricula have not kept pace with the needs of the international market. 3. Benefits and User Experience For the 30% of translators who do use specialized tools, the results were largely positive: • Productivity: 25% reported that the tools helped them finish work on time. • Quality: 20% noted an increase in the consistency of terms. • Output Value: 60% of respondents felt their overall translation output had been "impressive" since the advent of these tools, indicating that the advantages outweigh the disadvantages for those who adopt them. 4. Barriers to Adoption The 70% of translators who do not use CAT tools cited several overlapping reasons for their resistance: • High Cost: 70% of non-users identified the expensive nature of the software as their primary barrier. The researchers noted that tools can cost between €60 and €695, which is often prohibitive given local income levels. • Learning Curve: 62% of non-users (and 100% of users) agreed that the time involved in learning how to use these tools is "very long". • Market Impact: 45% of respondents rated the overall impact of technology on the Nigerian industry as "discouraging," with many citing a lack of professionalism and the unorganized state of the local market. | AE2: 1. Technology is "Indispensable" but Under-Utilised The researchers conclude that while state-of-the-art tools like Translation Memory (TM) and terminology management are indispensable to the profession, they have not yet made a great impact in Nigeria. The local market remains dominated by traditional methods—specifically hard-copy dictionaries and pen and paper—even among those who use basic word processors like Microsoft Word. 2. The Triad of Barriers: Cost, Time, and Misconception The study identifies three primary reasons why Nigerian translators are discouraged from adopting new technologies: • Economic Barriers: The expensive nature of the software is the most significant hurdle; 70% of non-users cited high costs (ranging from €60 to €695) as their reason for avoidance. • The Learning Curve: There is a consensus that the time involved in learning how to use these tools is "very long," which deters busy professionals from upgrading. • Conceptual Confusion: A major conclusion is that misconceptions about the technology itself hinder its acquisition. Since 50% of translators mistakenly believe TM is the same as fully automatic machine translation, they view the tools as unreliable or not useful for high-quality work. 3. Market Alienation and Professional Risks The researchers conclude that failing to adopt these tools has direct economic consequences for Nigerian translators: • Exclusion from International Jobs: International clients and organisations increasingly demand the use of TM and terminology management tools. Translators who do not use them face a lack of jobs from the global market. • Remuneration Issues: The study suggests that if translators cannot use tools to improve their speed and satisfy international standards, they will struggle to increase their income. 4. Failure of the Educational Pipeline The study concludes that academic institutions are failing to prepare the next generation of translators for the digital age. Although most translators were trained in environments where CAT tools existed, only 10% were actually taught how to use them in school. The authors warn that if this trend continues, Nigerian translators will remain unable to compete in an "ever-changing world of technology". 5. Proven Benefits for Early Adopters Despite the general resistance, the study concludes that for the small percentage of translators who do use the tools, the results are overwhelmingly positive: • Enhanced Quality: Users reported greater consistency of terms. • Increased Productivity: Users were more likely to finish work on time. • Job Satisfaction: 60% of respondents indicated their professional output had been "impressive" since adopting the tools, proving that the advantages far outweigh the disadvantages. | AF2: • State-of-the-art translation tools: A collective term for the modern software suite, including translation memory, voice recognition, and terminology management. • Sensitising: The core action recommended by the authors to awaken Nigerian translators to the need to embrace new technologies. • Under-utilised: The primary conclusion regarding the status of specialized translation software in Nigeria. • Expensive nature: Identified as a significant discouraging factor and the main reason why 70% of non-users avoid purchasing CAT tools. • Misconception: Specifically used to describe the confusion between Translation Memory (TM) and automatic Machine Translation (MT), which leads many to believe the tools are unreliable. • Consistency of terms: A primary benefit cited by those who successfully use the tools. • Impressive: The specific term used by 60% of respondents to evaluate their professional output since the advent of these tools. • Indispensable: The researchers' final assessment of the role of technology in the profession, regardless of its current low usage in the country. • Widely demanded: Refers to the technological requirements set by international organisations and global clients, which Nigerian translators are currently struggling to meet. | AG2: Linguistic challenges; Technical aspects; Ethical aspects | AH2: =+COUNTIFS('Coded Segments'!$C$2:$C$913,SLR_Covidence_Data_Extraction__66_files[[#This Row],[Study ID_1]],'Coded Segments'!$D$2:$D$913,SLR_Covidence_Data_Extraction__66_files[[#Headers],[Adoption (AD) > AD_High]]) -> 0 | AI2: =+COUNTIFS('Coded Segments'!$C$2:$C$913,SLR_Covidence_Data_Extraction__66_files[[#This Row],[Study ID_1]],'Coded Segments'!$D$2:$D$913,SLR_Covidence_Data_Extraction__66_files[[#Headers],[Adoption (AD) > AD_Moderate]]) -> 0 | AJ2: =+COUNTIFS('Coded Segments'!$C$2:$C$913,SLR_Covidence_Data_Extraction__66_files[[#This Row],[Study ID_1]],'Coded Segments'!$D$2:$D$913,SLR_Covidence_Data_Extraction__66_files[[#Headers],[Adoption (AD) > AD_Low]]) -> 0 | AK2: =+COUNTIFS('Coded Segments'!$C$2:$C$913,SLR_Covidence_Data_Extraction__66_files[[#This Row],[Study ID_1]],'Coded Segments'!$D$2:$D$913,SLR_Covidence_Data_Extraction__66_files[[#Headers],[Adoption (AD) > AD_None]]) -> 0 | AL2: =+COUNTIFS('Coded Segments'!$C$2:$C$913,SLR_Covidence_Data_Extraction__66_files[[#This Row],[Study ID_1]],'Coded Segments'!$D$2:$D$913,SLR_Covidence_Data_Extraction__66_files[[#Headers],[Attitude (ATT) > ATT_Negative]]) -> 2 | AM2: =+COUNTIFS('Coded Segments'!$C$2:$C$913,SLR_Covidence_Data_Extraction__66_files[[#This Row],[Study ID_1]],'Coded Segments'!$D$2:$D$913,SLR_Covidence_Data_Extraction__66_files[[#Headers],[Attitude (ATT) > ATT_Positive]]) -> 1 | AN2: =+COUNTIFS('Coded Segments'!$C$2:$C$913,SLR_Covidence_Data_Extraction__66_files[[#This Row],[Study ID_1]],'Coded Segments'!$D$2:$D$913,SLR_Covidence_Data_Extraction__66_files[[#Headers],[Ethical Concerns (EC) > EC_Bias]]) -> 0 | AO2: =+COUNTIFS('Coded Segments'!$C$2:$C$913,SLR_Covidence_Data_Extraction__66_files[[#This Row],[Study ID_1]],'Coded Segments'!$D$2:$D$913,SLR_Covidence_Data_Extraction__66_files[[#Headers],[Ethical Concerns (EC) > EC_Copyright]]) -> 0 | AP2: =+COUNTIFS('Coded Segments'!$C$2:$C$913,SLR_Covidence_Data_Extraction__66_files[[#This Row],[Study ID_1]],'Coded Segments'!$D$2:$D$913,SLR_Covidence_Data_Extraction__66_files[[#Headers],[Ethical Concerns (EC) > EC_Data safety & confidentiality]]) -> 0 | AQ2: =+COUNTIFS('Coded Segments'!$C$2:$C$913,SLR_Covidence_Data_Extraction__66_files[[#This Row],[Study ID_1]],'Coded Segments'!$D$2:$D$913,SLR_Covidence_Data_Extraction__66_files[[#Headers],[Ethical Concerns (EC) > EC_Environmental sustainability]]) -> 0 | AR2: =+COUNTIFS('Coded Segments'!$C$2:$C$913,SLR_Covidence_Data_Extraction__66_files[[#This Row],[Study ID_1]],'Coded Segments'!$D$2:$D$913,SLR_Covidence_Data_Extraction__66_files[[#Headers],[Ethical Concerns (EC) > EC_Payment]]) -> 1 | AS2: =+COUNTIFS('Coded Segments'!$C$2:$C$912,SLR_Covidence_Data_Extraction__66_files[[#This Row],[Study ID_1]],'Coded Segments'!$D$2:$D$912,SLR_Covidence_Data_Extraction__66_files[[#Headers],[Ethical Concerns (EC) > EC_Quality]]) -> 1 | AT2: =+COUNTIFS('Coded Segments'!$C$2:$C$913,SLR_Covidence_Data_Extraction__66_files[[#This Row],[Study ID_1]],'Coded Segments'!$D$2:$D$913,SLR_Covidence_Data_Extraction__66_files[[#Headers],[Ethical Concerns (EC) > EC_Translators’ role & status]]) -> 0 | AU2: =+COUNTIFS('Coded Segments'!$C$2:$C$913,SLR_Covidence_Data_Extraction__66_files[[#This Row],[Study ID_1]],'Coded Segments'!$D$2:$D$913,SLR_Covidence_Data_Extraction__66_files[[#Headers],[Ethical Concerns (EC) > EC_Other]]) -> 0 | AV2: =+COUNTIFS('Coded Segments'!$C$2:$C$913,SLR_Covidence_Data_Extraction__66_files[[#This Row],[Study ID_1]],'Coded Segments'!$D$2:$D$913,SLR_Covidence_Data_Extraction__66_files[[#Headers],[Literacy (LIT) > LIT_Generic]]) -> 0 | AW2: =+COUNTIFS('Coded Segments'!$C$2:$C$913,SLR_Covidence_Data_Extraction__66_files[[#This Row],[Study ID_1]],'Coded Segments'!$D$2:$D$913,SLR_Covidence_Data_Extraction__66_files[[#Headers],[Literacy (LIT) > LIT_None ]]) -> 1 | AX2: =+COUNTIFS('Coded Segments'!$C$2:$C$913,SLR_Covidence_Data_Extraction__66_files[[#This Row],[Study ID_1]],'Coded Segments'!$D$2:$D$913,SLR_Covidence_Data_Extraction__66_files[[#Headers],[Literacy (LIT) > LIT_Low ]]) -> 2 | AY2: =+COUNTIFS('Coded Segments'!$C$2:$C$913,SLR_Covidence_Data_Extraction__66_files[[#This Row],[Study ID_1]],'Coded Segments'!$D$2:$D$913,SLR_Covidence_Data_Extraction__66_files[[#Headers],[Literacy (LIT) > LIT_High]]) -> 0
A3: 31 | B3: 2SM3ZCXD | C3: Ruffo 2018 | D3: Human-Computer Interaction in Translation: Literary Translators on Technology and Their Roles | E3: Paola Ruffo E-mail: pr25@hw.ac.uk | F3: Heriot-Watt University Edinburgh, UK | G3: UK | H3: 2018/11 | I3: =LEFT(SLR_Covidence_Data_Extraction__66_files[[#This Row],[Publication date]],4) -> 2018 | J3: UK | K3: To achieve a richer understanding of the human and technological factors at play within the field of literary translation. | L3: Questionnaire | S3: 2018 | T3: 2018 | V3: Online | X3: This doctoral research project is funded by Heriot-Watt University and is supervised by Dr Marion Winters and Prof Graham Turner, under the auspices of the Centre for Translation and Interpreting Studies in Scotland (CTISS), Heriot-Watt University, Edinburgh, Scotland, UK. | Y3: Literary translators based in Edinburgh, UK | Z3: Professional translators | AA3: Literary | AB3: 8 | AC3: 8 | AD3: 1. Technology Confidence and Usage Gap • General vs. Specific Tech: While nearly all respondents felt very confident with general technology, this confidence did not extend to translation-specific tools. • Literary vs. Non-Literary Work: Respondents reported using zero specialized translation technology (CAT or MT) for their literary projects. However, five out of the eight participants did use CAT tools for their non-literary assignments. • Preferred Tools: For literary work, translators rely on "general" technology such as Microsoft Word, online dictionaries, spellcheckers, and time management software. 2. Professional Identity and Role Perception • The "Noble" Craft: Translators view their work as a noble activity rooted in art and passion, requiring deep cultural and linguistic knowledge. • Outsider Misunderstanding: A significant finding was a sense of isolation and frustration, as participants felt that people outside the profession fail to appreciate or understand the complexity of literary translation. 3. Attitudes Toward Technology • Interpretative Flexibility: Following the SCOT framework, translators make a sharp distinction between different types of technology. • Supportive vs. Threatening Tech: ◦ Positive: Translators praised the internet, corpora, and terminology tools as essential for research. They also valued online forums and communities as a way to combat professional isolation. ◦ Negative: CAT tools and Machine Translation (MT) are largely dismissed. Respondents believe these tools will never catch on in literature as they have in other sectors because they "threaten to steal the essence" of the creative process by ignoring uniquely human aspects. | AE3: 1. The "Interpretative Flexibility" of Technology A primary conclusion is that literary translators make a sharp distinction between different categories of digital tools. Following the Social Construction of Technology (SCOT) framework, they do not view technology as a single, deterministic force but rather interpret different tools through their own professional values. • Supportive Technology: Tools that facilitate research—such as the internet, corpora, and terminology tools—are highly praised and considered essential to the modern workflow. • Threatening Technology: CAT tools and Machine Translation (MT) are largely dismissed. The conclusion is that these tools are seen as ignoring the "peculiarly human aspects" of translation and are therefore viewed as incompatible with literature. 2. Preservation of the "Noble" Professional Identity The study concludes that the rejection of specialized translation technology is deeply tied to the translator’s self-perception and professional role. • Translators view their work as a "noble activity" rooted in art, passion, and profound cultural knowledge. • Because current automation (MT/CAT) focuses on efficiency and segments, translators conclude that these tools "threaten to steal the essence" of their creative activity. • There is a strong belief that while technology has transformed other sectors, it will "never catch on" in the literary field in the same way. 3. Technology as a Solution to Isolation A significant social conclusion is that technology serves a vital role in combating the professional isolation inherent in the craft. • Translators feel that those outside the profession fail to understand the complexity of their role, leading to frustration and a sense of being undervalued. • To mitigate this, they utilize online forums and digital communities to connect with colleagues, suggesting that "social" technology is far more welcome than "productive" technology. 4. The "Non-Literary" Bridge The data suggests that the use of technology is context-dependent rather than based on a lack of skill. • Even though respondents used zero specialized technology for literary work, the majority (five out of eight) reported using CAT tools for their non-literary assignments. • This leads to the conclusion that literary translators are technologically competent but choose to reject these tools for creative work because they do not align with the artistic requirements of the genre. | AF3: • Theoretical and methodological frameworks: Refers to the underlying structures of the study, specifically the Social Construction of Technology (SCOT) and interpretivist approach. • Personal narratives: Used to describe the individual stories and qualitative data gathered from translators about their professional experiences. • Shift from humanistic to technology-driven: Describes the transition of the translation profession in the digital age, which the study aims to document through translators' own perspectives. • Perceptions of their role in society: A core metric of the study, focusing on how literary translators view their own professional identity and how they believe "outsiders" perceive them. • Attitudes towards technology: Refers to the specific feelings (often mixed) that translators hold regarding digital tools, ranging from the internet to specialized CAT and MT software. • Preliminary findings: Highlights that the data presented (specifically the rejection of specialized tech in favour of supportive tools) represents the initial pilot phase of a larger ongoing project. | AG3: Technical aspects; Ethical aspects | AH3: =+COUNTIFS('Coded Segments'!$C$2:$C$913,SLR_Covidence_Data_Extraction__66_files[[#This Row],[Study ID_1]],'Coded Segments'!$D$2:$D$913,SLR_Covidence_Data_Extraction__66_files[[#Headers],[Adoption (AD) > AD_High]]) -> 0 | AI3: =+COUNTIFS('Coded Segments'!$C$2:$C$913,SLR_Covidence_Data_Extraction__66_files[[#This Row],[Study ID_1]],'Coded Segments'!$D$2:$D$913,SLR_Covidence_Data_Extraction__66_files[[#Headers],[Adoption (AD) > AD_Moderate]]) -> 0 | AJ3: =+COUNTIFS('Coded Segments'!$C$2:$C$913,SLR_Covidence_Data_Extraction__66_files[[#This Row],[Study ID_1]],'Coded Segments'!$D$2:$D$913,SLR_Covidence_Data_Extraction__66_files[[#Headers],[Adoption (AD) > AD_Low]]) -> 0 | AK3: =+COUNTIFS('Coded Segments'!$C$2:$C$913,SLR_Covidence_Data_Extraction__66_files[[#This Row],[Study ID_1]],'Coded Segments'!$D$2:$D$913,SLR_Covidence_Data_Extraction__66_files[[#Headers],[Adoption (AD) > AD_None]]) -> 1 | AL3: =+COUNTIFS('Coded Segments'!$C$2:$C$913,SLR_Covidence_Data_Extraction__66_files[[#This Row],[Study ID_1]],'Coded Segments'!$D$2:$D$913,SLR_Covidence_Data_Extraction__66_files[[#Headers],[Attitude (ATT) > ATT_Negative]]) -> 4 | AM3: =+COUNTIFS('Coded Segments'!$C$2:$C$913,SLR_Covidence_Data_Extraction__66_files[[#This Row],[Study ID_1]],'Coded Segments'!$D$2:$D$913,SLR_Covidence_Data_Extraction__66_files[[#Headers],[Attitude (ATT) > ATT_Positive]]) -> 0 | AN3: =+COUNTIFS('Coded Segments'!$C$2:$C$913,SLR_Covidence_Data_Extraction__66_files[[#This Row],[Study ID_1]],'Coded Segments'!$D$2:$D$913,SLR_Covidence_Data_Extraction__66_files[[#Headers],[Ethical Concerns (EC) > EC_Bias]]) -> 0 | AO3: =+COUNTIFS('Coded Segments'!$C$2:$C$913,SLR_Covidence_Data_Extraction__66_files[[#This Row],[Study ID_1]],'Coded Segments'!$D$2:$D$913,SLR_Covidence_Data_Extraction__66_files[[#Headers],[Ethical Concerns (EC) > EC_Copyright]]) -> 0 | AP3: =+COUNTIFS('Coded Segments'!$C$2:$C$913,SLR_Covidence_Data_Extraction__66_files[[#This Row],[Study ID_1]],'Coded Segments'!$D$2:$D$913,SLR_Covidence_Data_Extraction__66_files[[#Headers],[Ethical Concerns (EC) > EC_Data safety & confidentiality]]) -> 0 | AQ3: =+COUNTIFS('Coded Segments'!$C$2:$C$913,SLR_Covidence_Data_Extraction__66_files[[#This Row],[Study ID_1]],'Coded Segments'!$D$2:$D$913,SLR_Covidence_Data_Extraction__66_files[[#Headers],[Ethical Concerns (EC) > EC_Environmental sustainability]]) -> 0 | AR3: =+COUNTIFS('Coded Segments'!$C$2:$C$913,SLR_Covidence_Data_Extraction__66_files[[#This Row],[Study ID_1]],'Coded Segments'!$D$2:$D$913,SLR_Covidence_Data_Extraction__66_files[[#Headers],[Ethical Concerns (EC) > EC_Payment]]) -> 0 | AS3: =+COUNTIFS('Coded Segments'!$C$2:$C$912,SLR_Covidence_Data_Extraction__66_files[[#This Row],[Study ID_1]],'Coded Segments'!$D$2:$D$912,SLR_Covidence_Data_Extraction__66_files[[#Headers],[Ethical Concerns (EC) > EC_Quality]]) -> 3 | AT3: =+COUNTIFS('Coded Segments'!$C$2:$C$913,SLR_Covidence_Data_Extraction__66_files[[#This Row],[Study ID_1]],'Coded Segments'!$D$2:$D$913,SLR_Covidence_Data_Extraction__66_files[[#Headers],[Ethical Concerns (EC) > EC_Translators’ role & status]]) -> 0 | AU3: =+COUNTIFS('Coded Segments'!$C$2:$C$913,SLR_Covidence_Data_Extraction__66_files[[#This Row],[Study ID_1]],'Coded Segments'!$D$2:$D$913,SLR_Covidence_Data_Extraction__66_files[[#Headers],[Ethical Concerns (EC) > EC_Other]]) -> 0 | AV3: =+COUNTIFS('Coded Segments'!$C$2:$C$913,SLR_Covidence_Data_Extraction__66_files[[#This Row],[Study ID_1]],'Coded Segments'!$D$2:$D$913,SLR_Covidence_Data_Extraction__66_files[[#Headers],[Literacy (LIT) > LIT_Generic]]) -> 0 | AW3: =+COUNTIFS('Coded Segments'!$C$2:$C$913,SLR_Covidence_Data_Extraction__66_files[[#This Row],[Study ID_1]],'Coded Segments'!$D$2:$D$913,SLR_Covidence_Data_Extraction__66_files[[#Headers],[Literacy (LIT) > LIT_None ]]) -> 0 | AX3: =+COUNTIFS('Coded Segments'!$C$2:$C$913,SLR_Covidence_Data_Extraction__66_files[[#This Row],[Study ID_1]],'Coded Segments'!$D$2:$D$913,SLR_Covidence_Data_Extraction__66_files[[#Headers],[Literacy (LIT) > LIT_Low ]]) -> 0 | AY3: =+COUNTIFS('Coded Segments'!$C$2:$C$913,SLR_Covidence_Data_Extraction__66_files[[#This Row],[Study ID_1]],'Coded Segments'!$D$2:$D$913,SLR_Covidence_Data_Extraction__66_files[[#Headers],[Literacy (LIT) > LIT_High]]) -> 0
A4: 13 | B4: 4VYWHYMR | C4: Vieira 2020 | D4: Automation anxiety and translators | E4: Lucas Nunes Vieira E-mail: l.nunesvieira@bristol.ac.uk | F4: School of Modern Languages, University of Bristol, UK | G4: UK | H4: 2018/11/29 | I4: =LEFT(SLR_Covidence_Data_Extraction__66_files[[#This Row],[Publication date]],4) -> 2018 | J4: Worldwide | K4: To situate translators’ discourse on machine translation and its potential economic reverberations within the context of broader work automation phenomena and empirical information on the translation profession. | O4: Other: Translators’ blog and forum postings | S4: 2017/08/11 | T4: 2017/08/13 | U4: Social media | V4: Online | Y4: Translators who publish their views online | Z4: Professional translators | AA4: General | AB4: 50 | AD4: 1. Pay Grievances are Rooted in Business Practices, Not MT A primary finding of the research is that Machine Translation (MT) is a secondary issue when translators discuss pay. • Agency Pressure: The most frequent non-descriptive grievance regarding pay was downward pressure from agencies and clients. Translators expressed frustration that agencies shape sector models to suit their own business interests, driving rates down to "para-professional" levels. • Billing Techniques: While technology does impact pay, the concern is often not with the tool itself but with how it is used for billing. Translators criticised "discount structures" where MT leverage is billed according to established repetition rates used for human-confirmed translation memories, which they deemed unreasonable. • Mixed Economic Picture: National statistics and professional surveys do not corroborate a systematic downward trend in pay. While some sectors may experience falling rates, the study notes that for many, technology's downward effect on unit rates is often compensated by an increase in volume. 2. Criticism of MT Concerns Limitations, Not Competition The study found that translators’ famously negative stance on MT is often misunderstood; most criticisms are rooted in the technology’s limitations and market consequences rather than a fear of being "replaced". • Lack of Performance Anxiety: Most translators do not believe their professional skills compete with MT, noting that MT has significant errors and low quality. One participant noted they would only worry once computers start "writing great books". • Low-Quality Exploitation: Negative attitudes are frequently directed at the low quality MT provides and how clients use it as a low-cost appeal to save money, rather than an intrinsic aversion to the technology itself. • Contextual Awareness: Translators demonstrated a sophisticated understanding of MT's limits, such as its inability to distinguish between specific terms (e.g., "journal" vs "magazine") without well-known context. 3. Nature of Professional Online Discourse The corpus analysis revealed that the majority of online discourse is actually descriptive or technical. • Knowledge Sharing: The most frequent category of comments for both "rates" and "machine translation" involved offering and obtaining help, such as sharing knowledge on how to calculate quotes or discussing technical aspects of software. • Keywords: "Rate", "software", "computer", and "technology" were the most prominent terms, indicating that economic and technological issues are similarly weighted in the professional consciousness. 4. Automation Risk and "Polanyi's Paradox" The study contextualises these results within wider economic trends, such as the polarization of jobs. • Medium-Risk Categorization: While some models estimate translation to be a "medium-risk" occupation for automation (38% probability), the study argues that translation's reliance on creative and social intelligence acts as a "bottleneck" to full automation. • Complementary Tools: In most scenarios, technology assists rather than replaces translators. Tools like SDL Trados or memoQ allow translators to recycle fragments via translation memories but leave humans in charge of abstract decision-making and editing. Ultimately, the study concludes that in the short to medium term, automation is not a danger to the profession. Instead, the real risk lies in the fragmentation of the translator's role if professionals abandon technical domains in a "mass exodus" toward more creative sectors like transcreation. | AE4: 1. Automation is not an immediate threat The researcher concludes that in the short to medium term, automation is not a danger to the translation profession. This is because technology typically replaces specific repetitive tasks rather than entire occupations—a concept known as Polanyi’s paradox. In translation, tools like MT and translation memory (TM) serve to assist rather than replace human professionals, who remain essential for abstract decision-making and creative intelligence. 2. Misunderstanding of Translators' Stance on MT A central conclusion is that translators’ famously negative attitude towards Machine Translation (MT) is frequently misunderstood. The analysis suggests that: • Most criticisms are not rooted in a fear of being outperformed by machines; translators generally believe their professional skills do not compete with low-quality MT. • Instead, hostility is directed at the technology’s limitations and the negative market consequences—such as the "low-cost appeal" that allows clients to use MT as a way to save money at the expense of quality. 3. Pay Grievances are Business-Driven The sources conclude that MT is a secondary issue in translators’ complaints regarding pay. Most economic dissatisfaction is rooted in business practices, specifically: • The downward pressure from agencies that shape the sector to suit their own business models. • The "unreasonable" billing techniques where agencies apply discount structures intended for human-confirmed TMs to MT output. • The researcher notes that national statistics do not show a systematic downward trend in pay, suggesting that for many, technology's impact on rates is compensated by an increase in work volume. 4. Warning Against Market Fragmentation The study warns against a potential "mass exodus" of qualified translators from technical domains towards more creative sectors like transcreation. The author concludes that: • Hierarchising services (viewing creative work as "superior" to technical work) may lead to a narrowing of the role of translation. • Abandoning technical sectors could lead to de-professionalisation, where tasks are left to individuals with no translation training while the core linguistic work is fragmented. 5. Recommendation for a Broadened Professional Role Ultimately, the study calls for a broadening of the translator’s role. The researcher argues that: • Translators should be viewed as comprehensive communication professionals and consultants on cultural and technological issues, rather than just linguistic transcoders. • The industry should move away from "dystopian discourses" and instead focus on open dialogue and business models that integrate the role of translators across all domains. • In any debate regarding the future of the profession, MT cannot be decoupled from its economic effects and market reverberations. | AF4: • Market reverberations and economic effects: The central conclusion that technology cannot be viewed in isolation; its impact is inextricably linked to how it affects pay and business models. • Business practices: Identified as the primary source of translators' grievances regarding pay, rather than machine translation (MT) technology itself. • Work automation phenomena: The broader context in which the study situates translation, specifically referencing the automation of middle-skilled clerical work and a shifting demand for cognitive labour. • Alternative forms of management and ownership: A proposed area for future experimentation to alleviate pressure from clients and agencies on translation rates. • Comprehensive communication professional: The recommended expanded role for translators, where they provide advice to end-clients on technology and cultural issues. • Automation resistance of creative tasks: A concept from work automation literature used to explain why creative domains are less likely to be fully automated. • De-professionalization: A warned-at consequence of an "exodus" of qualified translators from technical fields toward creative ones, which could lead to a narrowing of the concept of translation. • Dystopian discourses: The term the author uses for overly pessimistic narratives about the future of translation, which he suggests should be approached with caution. • Automation anxiety: The psychological state or industry sentiment the author seeks to address through open dialogue and the integration of translators across all domains. | AG4: Working conditions; Ethical aspects | AH4: =+COUNTIFS('Coded Segments'!$C$2:$C$913,SLR_Covidence_Data_Extraction__66_files[[#This Row],[Study ID_1]],'Coded Segments'!$D$2:$D$913,SLR_Covidence_Data_Extraction__66_files[[#Headers],[Adoption (AD) > AD_High]]) -> 0 | AI4: =+COUNTIFS('Coded Segments'!$C$2:$C$913,SLR_Covidence_Data_Extraction__66_files[[#This Row],[Study ID_1]],'Coded Segments'!$D$2:$D$913,SLR_Covidence_Data_Extraction__66_files[[#Headers],[Adoption (AD) > AD_Moderate]]) -> 0 | AJ4: =+COUNTIFS('Coded Segments'!$C$2:$C$913,SLR_Covidence_Data_Extraction__66_files[[#This Row],[Study ID_1]],'Coded Segments'!$D$2:$D$913,SLR_Covidence_Data_Extraction__66_files[[#Headers],[Adoption (AD) > AD_Low]]) -> 0 | AK4: =+COUNTIFS('Coded Segments'!$C$2:$C$913,SLR_Covidence_Data_Extraction__66_files[[#This Row],[Study ID_1]],'Coded Segments'!$D$2:$D$913,SLR_Covidence_Data_Extraction__66_files[[#Headers],[Adoption (AD) > AD_None]]) -> 0 | AL4: =+COUNTIFS('Coded Segments'!$C$2:$C$913,SLR_Covidence_Data_Extraction__66_files[[#This Row],[Study ID_1]],'Coded Segments'!$D$2:$D$913,SLR_Covidence_Data_Extraction__66_files[[#Headers],[Attitude (ATT) > ATT_Negative]]) -> 5 | AM4: =+COUNTIFS('Coded Segments'!$C$2:$C$913,SLR_Covidence_Data_Extraction__66_files[[#This Row],[Study ID_1]],'Coded Segments'!$D$2:$D$913,SLR_Covidence_Data_Extraction__66_files[[#Headers],[Attitude (ATT) > ATT_Positive]]) -> 3 | AN4: =+COUNTIFS('Coded Segments'!$C$2:$C$913,SLR_Covidence_Data_Extraction__66_files[[#This Row],[Study ID_1]],'Coded Segments'!$D$2:$D$913,SLR_Covidence_Data_Extraction__66_files[[#Headers],[Ethical Concerns (EC) > EC_Bias]]) -> 0 | AO4: =+COUNTIFS('Coded Segments'!$C$2:$C$913,SLR_Covidence_Data_Extraction__66_files[[#This Row],[Study ID_1]],'Coded Segments'!$D$2:$D$913,SLR_Covidence_Data_Extraction__66_files[[#Headers],[Ethical Concerns (EC) > EC_Copyright]]) -> 0 | AP4: =+COUNTIFS('Coded Segments'!$C$2:$C$913,SLR_Covidence_Data_Extraction__66_files[[#This Row],[Study ID_1]],'Coded Segments'!$D$2:$D$913,SLR_Covidence_Data_Extraction__66_files[[#Headers],[Ethical Concerns (EC) > EC_Data safety & confidentiality]]) -> 0 | AQ4: =+COUNTIFS('Coded Segments'!$C$2:$C$913,SLR_Covidence_Data_Extraction__66_files[[#This Row],[Study ID_1]],'Coded Segments'!$D$2:$D$913,SLR_Covidence_Data_Extraction__66_files[[#Headers],[Ethical Concerns (EC) > EC_Environmental sustainability]]) -> 0 | AR4: =+COUNTIFS('Coded Segments'!$C$2:$C$913,SLR_Covidence_Data_Extraction__66_files[[#This Row],[Study ID_1]],'Coded Segments'!$D$2:$D$913,SLR_Covidence_Data_Extraction__66_files[[#Headers],[Ethical Concerns (EC) > EC_Payment]]) -> 4 | AS4: =+COUNTIFS('Coded Segments'!$C$2:$C$912,SLR_Covidence_Data_Extraction__66_files[[#This Row],[Study ID_1]],'Coded Segments'!$D$2:$D$912,SLR_Covidence_Data_Extraction__66_files[[#Headers],[Ethical Concerns (EC) > EC_Quality]]) -> 2 | AT4: =+COUNTIFS('Coded Segments'!$C$2:$C$913,SLR_Covidence_Data_Extraction__66_files[[#This Row],[Study ID_1]],'Coded Segments'!$D$2:$D$913,SLR_Covidence_Data_Extraction__66_files[[#Headers],[Ethical Concerns (EC) > EC_Translators’ role & status]]) -> 3 | AU4: =+COUNTIFS('Coded Segments'!$C$2:$C$913,SLR_Covidence_Data_Extraction__66_files[[#This Row],[Study ID_1]],'Coded Segments'!$D$2:$D$913,SLR_Covidence_Data_Extraction__66_files[[#Headers],[Ethical Concerns (EC) > EC_Other]]) -> 0 | AV4: =+COUNTIFS('Coded Segments'!$C$2:$C$913,SLR_Covidence_Data_Extraction__66_files[[#This Row],[Study ID_1]],'Coded Segments'!$D$2:$D$913,SLR_Covidence_Data_Extraction__66_files[[#Headers],[Literacy (LIT) > LIT_Generic]]) -> 0 | AW4: =+COUNTIFS('Coded Segments'!$C$2:$C$913,SLR_Covidence_Data_Extraction__66_files[[#This Row],[Study ID_1]],'Coded Segments'!$D$2:$D$913,SLR_Covidence_Data_Extraction__66_files[[#Headers],[Literacy (LIT) > LIT_None ]]) -> 0 | AX4: =+COUNTIFS('Coded Segments'!$C$2:$C$913,SLR_Covidence_Data_Extraction__66_files[[#This Row],[Study ID_1]],'Coded Segments'!$D$2:$D$913,SLR_Covidence_Data_Extraction__66_files[[#Headers],[Literacy (LIT) > LIT_Low ]]) -> 0 | AY4: =+COUNTIFS('Coded Segments'!$C$2:$C$913,SLR_Covidence_Data_Extraction__66_files[[#This Row],[Study ID_1]],'Coded Segments'!$D$2:$D$913,SLR_Covidence_Data_Extraction__66_files[[#Headers],[Literacy (LIT) > LIT_High]]) -> 0
A5: 36 | B5: D7X889BT | C5: Fung 2018 | D5: Post-Editing in the Wild: An Empirical Study of Chinese-to-English Professional Translators in New Zealand | E5: Yuen May Fung | F5: School of Cultures, Languages and Linguistics, The University of Auckland | G5: New Zealand | H5: 2018 | I5: =LEFT(SLR_Covidence_Data_Extraction__66_files[[#This Row],[Publication date]],4) -> 2018 | J5: New Zealand | K5: • Understanding the PE Process and Product: The study seeks to describe how these translators execute a post-editing task on a technical patent text, focusing on their productivity, the quality of the final output, and the specific types of textual changes and errors made. • Correlating Perception and Actuality: It aims to examine the relationships between subjective self-reported data (such as perceived effort) and objective measured data (such as actual time spent and number of edits) to determine if specific measurements can serve as reliable proxies for post-editing effort. • Analysing the Impact of Personal Attributes: The research explores how a translator’s attitude towards machine translation (MT), their in-domain (patent) experience, and their dominant working language (L1 versus L2) impact their overall performance. | L5: Questionnaire | N5: Interviews | U5: Universities | V5: Online | W5: Offline | Y5: Professional Chinese-to-English translators | Z5: Professional translators | AA5: General | AB5: 8 | AC5: 8 | AD5: Task Execution and Productivity • Time and Efficiency: The average time taken to complete the post-editing of 332 machine-translated words was 55.7 minutes, though individual durations varied significantly from 26 to 79.6 minutes. • Productivity Levels: The group’s mean productivity was 3,256 words per day, which is higher than the industry benchmark for manual translation (2,500 words) but lower than the standard for full post-editing (5,000 words). • Workflow Distribution: Participants spent the majority of their time (71.5%) on the first post-editing pass, while 13.5% was dedicated to preparation/research and 9.8% to self-revision and review. • Editing Types: The most frequent textual changes were substitutions (45%), followed by deletions (25%), insertions (17%), and re-ordering (13%). All participants exhibited a similar distribution pattern of these edit types. Technology Adoption and Research Habits • Heavy Use of Free MT: A notable result was the frequent and conspicuous use of free online machine translation systems (such as Google Translate and Youdao fanyi) as a research tool during the task. • Online Research: Online resources accounted for over 71% of total preparation time, with online MT sites being the most used resource (46%), followed by search engines and dictionaries. Quality and Error Analysis • Error Generation: The participants introduced 107 new errors during the process, with meaning deletion being the most frequent error type (40.2%). • Overlooked Errors: The group missed 23 existing machine translation errors, the majority of which were related to accuracy (meaning) rather than fluency (grammar). • Metric Scores: All but one participant produced a final text that was an improvement over the raw MT baseline according to BLEU and TER scores. Correlations Between Effort and Actuality • Perceived vs. Actual Effort: At the sentence level, there was a weak but statistically significant correlation between how difficult a translator perceived a sentence to be and the actual time and number of edits required to fix it. • Influence of Sentence Length: Contrary to some previous studies, sentence length did not influence perceived effort ratings, meaning translators did not automatically rate longer sentences as more difficult. However, longer MT sentences did correlate with a higher number of edit events. Impact of Professional Attributes • Attitude towards MT: Translators with a more positive attitude towards technology spent more time on the first PE pass, less time on self-revision, and produced higher quality output (as indicated by lower TER scores). • In-domain Experience: Participants with prior patent translation experience were significantly more productive and made fewer accuracy-related errors than those without such experience. • The Directionality Factor: A major result was that native English speakers (L1) did not perform significantly differently from non-native English speakers (L2) in terms of productivity or overall quality. While L1 translators introduced slightly fewer fluency-related errors, this difference was not statistically significant. | AE5: Significant Individual Variation The study concludes that there is considerable variation among professional translators in terms of their post-editing style, productivity, and the quality of their final output. Despite similar professional backgrounds, individuals utilised different strategies to manage the task, with total task durations ranging from 26 to nearly 80 minutes. The Impact of Attitude and Experience A primary conclusion is that a translator's attitude toward machine translation (MT) directly influences their work. • Positive Attitude: Participants with a more favourable view of the technology tended to spend more effort improving the output and achieved significantly better quality results. • Domain Expertise: In-domain (patent) translation experience and formal translator training were concluded to be the primary drivers of higher productivity and better accuracy. The Role of Native Language (Directionality) A critical conclusion of the study is that language directionality does not significantly affect performance. The research found no empirical evidence that native English speakers (L1) performed better than non-native speakers (L2) regarding post-editing productivity or final quality. This suggests that post-editing may help "level the playing field" for translators working into their second language. Frequent Use of Free Online MT The study concludes that professional translators frequently and conspicuously use free online machine translation systems (such as Google Translate) as research and inspiration tools, even when they have no formal prior experience in post-editing. Online MT was the most used resource during task preparation, accounting for 46% of total online research time. Correlating Perception and Actuality The researcher concludes that subjective perception of effort is a reasonably valid, though weak, indicator of actual work. • Correlations: There were statistically significant correlations between how difficult a translator perceived a sentence to be and the actual time and number of edits required to fix it. • Sentence Length: Contrary to some previous theories, sentence length did not influence perceived effort, meaning translators did not view longer sentences as inherently more difficult than shorter ones. Quality Improvement and Error Generation The study concludes that while most translators produce an output that is a measurable improvement over the raw MT baseline, the process is prone to human error. Participants introduced numerous new errors (predominantly meaning deletions) and missed existing MT errors (primarily related to accuracy), highlighting that post-editing requires high levels of vigilance and specific training. Human-Machine Cooperation Ultimately, the study serves as an empirical basis for advancing the understanding of post-editing as an increasingly important form of human-machine cooperation. It concludes that as post-editing becomes a mainstream service, there is an urgent need to develop specialised training strategies, particularly for those working in their second language, to future-proof the livelihoods of professional translators. | AF5: • PE process and product: The two primary aspects of the study, covering both the actions taken during editing and the resulting translated text. • Productivity and final quality: The core metrics used to assess the commercial viability and professional success of post-editing. • Post-editor variation: A term describing the observation that translators exhibit diverse individual behaviours and styles when performing identical tasks. • Perceived, temporal, technical, and cognitive effort: The multi-dimensional framework used to measure the "work" involved in post-editing. • Acclimatisation effect: A concept suggesting that post-editors expend more effort at the beginning of a task while familiarising themselves with the text. • Fatigue effect: The negative impact on quality that occurs when participants lose concentration or tire towards the end of a translation task. • Language directionality: The distinction between translating into a native language (L1) versus a second language (L2), which the study concludes has no significant impact on post-editing performance. • Ecologically valid methods: Research approaches designed to reflect real-world scenarios and naturalistic environments rather than strictly controlled laboratory settings. • Construct validity: A research standard concerning the degree to which a test measures what it claims to measure, which the author notes can sometimes conflict with ecological validity. • Edit density indicator (EDI): A potential new metric introduced by the author to quantify the amount of editing performed on a machine-translated sentence. • Aptitude profile: A proposed diagnostic framework to help identify individuals best suited for professional post-editing roles. • Translator-computer interaction (TCI): The specific sub-field of human-technology cooperation that focuses on how translators engage with digital tools. • Cognitive translatology: An emerging area of the "scientific study of translation" that incorporates diagnostic techniques to measure brain activity and mental processes. | AG5: Linguistic challenges; Technical aspects; Training needs; Working conditions; Ethical aspects | AH5: =+COUNTIFS('Coded Segments'!$C$2:$C$913,SLR_Covidence_Data_Extraction__66_files[[#This Row],[Study ID_1]],'Coded Segments'!$D$2:$D$913,SLR_Covidence_Data_Extraction__66_files[[#Headers],[Adoption (AD) > AD_High]]) -> 0 | AI5: =+COUNTIFS('Coded Segments'!$C$2:$C$913,SLR_Covidence_Data_Extraction__66_files[[#This Row],[Study ID_1]],'Coded Segments'!$D$2:$D$913,SLR_Covidence_Data_Extraction__66_files[[#Headers],[Adoption (AD) > AD_Moderate]]) -> 2 | AJ5: =+COUNTIFS('Coded Segments'!$C$2:$C$913,SLR_Covidence_Data_Extraction__66_files[[#This Row],[Study ID_1]],'Coded Segments'!$D$2:$D$913,SLR_Covidence_Data_Extraction__66_files[[#Headers],[Adoption (AD) > AD_Low]]) -> 0 | AK5: =+COUNTIFS('Coded Segments'!$C$2:$C$913,SLR_Covidence_Data_Extraction__66_files[[#This Row],[Study ID_1]],'Coded Segments'!$D$2:$D$913,SLR_Covidence_Data_Extraction__66_files[[#Headers],[Adoption (AD) > AD_None]]) -> 0 | AL5: =+COUNTIFS('Coded Segments'!$C$2:$C$913,SLR_Covidence_Data_Extraction__66_files[[#This Row],[Study ID_1]],'Coded Segments'!$D$2:$D$913,SLR_Covidence_Data_Extraction__66_files[[#Headers],[Attitude (ATT) > ATT_Negative]]) -> 0 | AM5: =+COUNTIFS('Coded Segments'!$C$2:$C$913,SLR_Covidence_Data_Extraction__66_files[[#This Row],[Study ID_1]],'Coded Segments'!$D$2:$D$913,SLR_Covidence_Data_Extraction__66_files[[#Headers],[Attitude (ATT) > ATT_Positive]]) -> 3 | AN5: =+COUNTIFS('Coded Segments'!$C$2:$C$913,SLR_Covidence_Data_Extraction__66_files[[#This Row],[Study ID_1]],'Coded Segments'!$D$2:$D$913,SLR_Covidence_Data_Extraction__66_files[[#Headers],[Ethical Concerns (EC) > EC_Bias]]) -> 0 | AO5: =+COUNTIFS('Coded Segments'!$C$2:$C$913,SLR_Covidence_Data_Extraction__66_files[[#This Row],[Study ID_1]],'Coded Segments'!$D$2:$D$913,SLR_Covidence_Data_Extraction__66_files[[#Headers],[Ethical Concerns (EC) > EC_Copyright]]) -> 0 | AP5: =+COUNTIFS('Coded Segments'!$C$2:$C$913,SLR_Covidence_Data_Extraction__66_files[[#This Row],[Study ID_1]],'Coded Segments'!$D$2:$D$913,SLR_Covidence_Data_Extraction__66_files[[#Headers],[Ethical Concerns (EC) > EC_Data safety & confidentiality]]) -> 0 | AQ5: =+COUNTIFS('Coded Segments'!$C$2:$C$913,SLR_Covidence_Data_Extraction__66_files[[#This Row],[Study ID_1]],'Coded Segments'!$D$2:$D$913,SLR_Covidence_Data_Extraction__66_files[[#Headers],[Ethical Concerns (EC) > EC_Environmental sustainability]]) -> 0 | AR5: =+COUNTIFS('Coded Segments'!$C$2:$C$913,SLR_Covidence_Data_Extraction__66_files[[#This Row],[Study ID_1]],'Coded Segments'!$D$2:$D$913,SLR_Covidence_Data_Extraction__66_files[[#Headers],[Ethical Concerns (EC) > EC_Payment]]) -> 0 | AS5: =+COUNTIFS('Coded Segments'!$C$2:$C$912,SLR_Covidence_Data_Extraction__66_files[[#This Row],[Study ID_1]],'Coded Segments'!$D$2:$D$912,SLR_Covidence_Data_Extraction__66_files[[#Headers],[Ethical Concerns (EC) > EC_Quality]]) -> 3 | AT5: =+COUNTIFS('Coded Segments'!$C$2:$C$913,SLR_Covidence_Data_Extraction__66_files[[#This Row],[Study ID_1]],'Coded Segments'!$D$2:$D$913,SLR_Covidence_Data_Extraction__66_files[[#Headers],[Ethical Concerns (EC) > EC_Translators’ role & status]]) -> 0 | AU5: =+COUNTIFS('Coded Segments'!$C$2:$C$913,SLR_Covidence_Data_Extraction__66_files[[#This Row],[Study ID_1]],'Coded Segments'!$D$2:$D$913,SLR_Covidence_Data_Extraction__66_files[[#Headers],[Ethical Concerns (EC) > EC_Other]]) -> 0 | AV5: =+COUNTIFS('Coded Segments'!$C$2:$C$913,SLR_Covidence_Data_Extraction__66_files[[#This Row],[Study ID_1]],'Coded Segments'!$D$2:$D$913,SLR_Covidence_Data_Extraction__66_files[[#Headers],[Literacy (LIT) > LIT_Generic]]) -> 3 | AW5: =+COUNTIFS('Coded Segments'!$C$2:$C$913,SLR_Covidence_Data_Extraction__66_files[[#This Row],[Study ID_1]],'Coded Segments'!$D$2:$D$913,SLR_Covidence_Data_Extraction__66_files[[#Headers],[Literacy (LIT) > LIT_None ]]) -> 0 | AX5: =+COUNTIFS('Coded Segments'!$C$2:$C$913,SLR_Covidence_Data_Extraction__66_files[[#This Row],[Study ID_1]],'Coded Segments'!$D$2:$D$913,SLR_Covidence_Data_Extraction__66_files[[#Headers],[Literacy (LIT) > LIT_Low ]]) -> 0 | AY5: =+COUNTIFS('Coded Segments'!$C$2:$C$913,SLR_Covidence_Data_Extraction__66_files[[#This Row],[Study ID_1]],'Coded Segments'!$D$2:$D$913,SLR_Covidence_Data_Extraction__66_files[[#Headers],[Literacy (LIT) > LIT_High]]) -> 0
A6: 57 | B6: W44GKG8M | C6: Blagodarna 2018 | D6: Insights into post-editors’ profiles and post-editing practices | E6: Olena Blagodarna E-mail: olena.blagodarna@e-campus.uab.cat ORCID: 0000-0001-5234-7119 | F6: Universitat Autònoma de Barcelona | G6: Spain | H6: 2018/12/18 | I6: =LEFT(SLR_Covidence_Data_Extraction__66_files[[#This Row],[Publication date]],4) -> 2018 | J6: Spain | K6: The aim of this article is to provide an updated snapshot of post-editors’ profiles and working routines. | L6: Questionnaire | P6: - | Q6: - | R6: 15 | U6: Social media; Professional associations networks | V6: Online | X6: ProjecTA project Translation projects with Statistical Machine Translation and Postediting, grant number FFI2013-46041-R [MINECO / FEDER, UE; Principal researcher: Dr. Olga Torres Hostench, Grup Tradumàtica, UAB] | Y6: Individuals working across the broad spectrum of MTPE-related activities. | Z6: Professional translators | AA6: General | AB6: 124 | AC6: 124 | AD6: Professional Profiles and Experience • The Experience Gap: While translation experience generally increases with a respondent's age, experience in post-editing (PE) is more heterogeneous. Notably, no participant in the study reported having more years of experience in PE than in traditional translation. • A Newer Occupation: The majority of respondents have less than 10 years of experience in PE, confirming that it is a relatively new professional occupation. Younger participants did not show a higher level of involvement in PE compared to their older colleagues. • Language Distribution: English emerged as the most popular source and target language. While European languages are dominant, the results show MT gaining traction for high volumes in non-European languages such as Japanese and Hebrew. Productivity and Compensation • Throughput Rates: The perceived average productivity for the relative majority of participants falls between 300 and 700 words per hour (WPH). Specifically, the 500–700 WPH range was the most frequent rate reported. • The Experience Advantage: A sub-group of more experienced post-editors (those with over five years of experience) reported significantly higher productivity, skewed towards 900 to over 1,000 WPH. • Rate-Setting Metrics: The most common criterion for establishing PE rates is the number of source text (ST) words, followed by hourly or daily rates. Calculating rates based on the "number of edits" is the least common practice, likely because the number of changes may not accurately reflect the actual effort involved. Workflow and Common Practices • Prevalence of Full PE: The study found a much higher frequency of "full PE" assignments (aiming for human-like quality) compared to "light PE". Nearly half of the respondents perform light PE in fewer than 10% of their projects, while performing full PE in more than 70% of their projects. • Task Routine: The most common preparation task is the evaluation of raw MT output quality to decide if it should be post-edited or translated from scratch. While automation of some operations (like "search-replace") is common, providing feedback to IT teams to improve MT engines is scarce. • Typical Assignment Materials: Post-editors typically receive a source text file accompanied by either raw MT output or a translation memory (TM) containing segments of specified origin. Tool Usage and Subject Domains • Instrumental Competence: Translators rely heavily on TM systems and generic tools (such as Word or Excel) for PE tasks. The use of specialised PE environments (e.g., PET) is very rare in professional workflows. • Dominant Fields: The most regular domains for MTPE are IT, software, website localisation, and e-commerce. Other common fields include Law, Tourism, and Entertainment, whereas PE projects in Real Estate or Social Sciences are scarce | AE6: A New and Emerging Professional Occupation The study concludes that post-editing is a "relatively new professional occupation". This is evidenced by the fact that the majority of respondents have less than 10 years of experience in the field, and none of the participants reported having more years of experience in PE than in traditional translation. The researchers conclude that the role of the translator is fundamentally changing in light of recent developments in the machine translation post-editing (MTPE) sector. The Dominance of "Full PE" A salient conclusion is the strong trend towards "full PE" assignments. The sources indicate that the industry is moving away from "light" edits toward requiring "human-like" output quality, particularly for IT-related content. This shift suggests that the market increasingly views MTPE as a viable method for producing high-quality final products rather than just "gist" translations. The Experience-Productivity Correlation The researcher concludes that professional experience is a primary driver of efficiency. While the general average for throughput is between 300 and 700 words per hour (WPH), experienced post-editors (those with over five years in the role) consistently achieve significantly higher rates, reaching 900 to over 1,000 WPH. Tool Usage and Workflow Gaps The study identifies a disconnect between available technology and actual professional practice: • Reliance on Generic Tools: Most post-editors rely on translation memory (TM) systems and generic software (like Word or Excel); notably, specialised PE instruments (such as PET) are currently not common in professional routines. • Lack of Feedback Loops: Translators are rarely involved in providing feedback to IT teams to improve MT engines. The author concludes this may be due to a lack of necessary skills, a lack of opportunity provided by language service providers (LSPs), or a perception that such practices are irrelevant. Implications for Academia and Training The study concludes that these empirical findings should serve as a reference point for tailoring translator training programs to meet market demands. • Integrated Approach: Training should go beyond basic industry requirements to focus on a broader scope of competences, including terminology, translation technology, and project management. • Balancing Expectation and Agency: The author concludes that academia must find a balance between teaching what the industry expects and enhancing trainees' expertise so that they can "go beyond such expectations" and exert more control over the MTPE process. | AF6: • Professional profiles and routines: The core focus of the study, referring to the background, experience, and daily working habits of language experts. • Current tendencies in the MTPE field: The emerging patterns and widespread practices within the machine translation post-editing sector. • PE throughput rates: The measurement of productivity, which the study concludes typically falls between 300 and 700 words per hour for the majority of participants. • New professional occupation: A term used to describe post-editing, noting that most practitioners have fewer than 10 years of experience in the role. • Full PE: The most common type of assignment, particularly for IT-related content, involving editing machine output to reach "human-like" quality. • PE workflow: The sequence of tasks in an assignment, typically starting with an ST file accompanied by raw MT output or a specified TM. • Automation of PE operations: The use of technical functions (such as 'search-replace') to handle repetitive editing tasks before or during the process. • Specialized PE instruments: Tools specifically designed for post-editing (such as PET) which the author concludes are currently not very common in professional workflows. • Instrumental and technical skills: The practical abilities deployed by post-editors that differentiate their role from traditional translation. • Changing role of translators: The shift in professional identity necessitated by recent developments and market demands in the MTPE sector. • Scope of competences: The specific skill sets currently required by post-editors, including Terminology, Translation Technology, Entrepreneurship, and Project Management. • Integrated approach to translator training: The recommended educational strategy that seeks to balance industry expectations with the enhancement of trainees’ expertise. • Drafting curricula: The process of creating training programs that align with the empirical findings of the market while allowing students to go beyond basic industry requirements. | AG6: Technical aspects; Training needs; Working conditions; Ethical aspects | AH6: =+COUNTIFS('Coded Segments'!$C$2:$C$913,SLR_Covidence_Data_Extraction__66_files[[#This Row],[Study ID_1]],'Coded Segments'!$D$2:$D$913,SLR_Covidence_Data_Extraction__66_files[[#Headers],[Adoption (AD) > AD_High]]) -> 1 | AI6: =+COUNTIFS('Coded Segments'!$C$2:$C$913,SLR_Covidence_Data_Extraction__66_files[[#This Row],[Study ID_1]],'Coded Segments'!$D$2:$D$913,SLR_Covidence_Data_Extraction__66_files[[#Headers],[Adoption (AD) > AD_Moderate]]) -> 0 | AJ6: =+COUNTIFS('Coded Segments'!$C$2:$C$913,SLR_Covidence_Data_Extraction__66_files[[#This Row],[Study ID_1]],'Coded Segments'!$D$2:$D$913,SLR_Covidence_Data_Extraction__66_files[[#Headers],[Adoption (AD) > AD_Low]]) -> 0 | AK6: =+COUNTIFS('Coded Segments'!$C$2:$C$913,SLR_Covidence_Data_Extraction__66_files[[#This Row],[Study ID_1]],'Coded Segments'!$D$2:$D$913,SLR_Covidence_Data_Extraction__66_files[[#Headers],[Adoption (AD) > AD_None]]) -> 0 | AL6: =+COUNTIFS('Coded Segments'!$C$2:$C$913,SLR_Covidence_Data_Extraction__66_files[[#This Row],[Study ID_1]],'Coded Segments'!$D$2:$D$913,SLR_Covidence_Data_Extraction__66_files[[#Headers],[Attitude (ATT) > ATT_Negative]]) -> 0 | AM6: =+COUNTIFS('Coded Segments'!$C$2:$C$913,SLR_Covidence_Data_Extraction__66_files[[#This Row],[Study ID_1]],'Coded Segments'!$D$2:$D$913,SLR_Covidence_Data_Extraction__66_files[[#Headers],[Attitude (ATT) > ATT_Positive]]) -> 0 | AN6: =+COUNTIFS('Coded Segments'!$C$2:$C$913,SLR_Covidence_Data_Extraction__66_files[[#This Row],[Study ID_1]],'Coded Segments'!$D$2:$D$913,SLR_Covidence_Data_Extraction__66_files[[#Headers],[Ethical Concerns (EC) > EC_Bias]]) -> 0 | AO6: =+COUNTIFS('Coded Segments'!$C$2:$C$913,SLR_Covidence_Data_Extraction__66_files[[#This Row],[Study ID_1]],'Coded Segments'!$D$2:$D$913,SLR_Covidence_Data_Extraction__66_files[[#Headers],[Ethical Concerns (EC) > EC_Copyright]]) -> 0 | AP6: =+COUNTIFS('Coded Segments'!$C$2:$C$913,SLR_Covidence_Data_Extraction__66_files[[#This Row],[Study ID_1]],'Coded Segments'!$D$2:$D$913,SLR_Covidence_Data_Extraction__66_files[[#Headers],[Ethical Concerns (EC) > EC_Data safety & confidentiality]]) -> 0 | AQ6: =+COUNTIFS('Coded Segments'!$C$2:$C$913,SLR_Covidence_Data_Extraction__66_files[[#This Row],[Study ID_1]],'Coded Segments'!$D$2:$D$913,SLR_Covidence_Data_Extraction__66_files[[#Headers],[Ethical Concerns (EC) > EC_Environmental sustainability]]) -> 0 | AR6: =+COUNTIFS('Coded Segments'!$C$2:$C$913,SLR_Covidence_Data_Extraction__66_files[[#This Row],[Study ID_1]],'Coded Segments'!$D$2:$D$913,SLR_Covidence_Data_Extraction__66_files[[#Headers],[Ethical Concerns (EC) > EC_Payment]]) -> 0 | AS6: =+COUNTIFS('Coded Segments'!$C$2:$C$912,SLR_Covidence_Data_Extraction__66_files[[#This Row],[Study ID_1]],'Coded Segments'!$D$2:$D$912,SLR_Covidence_Data_Extraction__66_files[[#Headers],[Ethical Concerns (EC) > EC_Quality]]) -> 2 | AT6: =+COUNTIFS('Coded Segments'!$C$2:$C$913,SLR_Covidence_Data_Extraction__66_files[[#This Row],[Study ID_1]],'Coded Segments'!$D$2:$D$913,SLR_Covidence_Data_Extraction__66_files[[#Headers],[Ethical Concerns (EC) > EC_Translators’ role & status]]) -> 0 | AU6: =+COUNTIFS('Coded Segments'!$C$2:$C$913,SLR_Covidence_Data_Extraction__66_files[[#This Row],[Study ID_1]],'Coded Segments'!$D$2:$D$913,SLR_Covidence_Data_Extraction__66_files[[#Headers],[Ethical Concerns (EC) > EC_Other]]) -> 0 | AV6: =+COUNTIFS('Coded Segments'!$C$2:$C$913,SLR_Covidence_Data_Extraction__66_files[[#This Row],[Study ID_1]],'Coded Segments'!$D$2:$D$913,SLR_Covidence_Data_Extraction__66_files[[#Headers],[Literacy (LIT) > LIT_Generic]]) -> 1 | AW6: =+COUNTIFS('Coded Segments'!$C$2:$C$913,SLR_Covidence_Data_Extraction__66_files[[#This Row],[Study ID_1]],'Coded Segments'!$D$2:$D$913,SLR_Covidence_Data_Extraction__66_files[[#Headers],[Literacy (LIT) > LIT_None ]]) -> 0 | AX6: =+COUNTIFS('Coded Segments'!$C$2:$C$913,SLR_Covidence_Data_Extraction__66_files[[#This Row],[Study ID_1]],'Coded Segments'!$D$2:$D$913,SLR_Covidence_Data_Extraction__66_files[[#Headers],[Literacy (LIT) > LIT_Low ]]) -> 0 | AY6: =+COUNTIFS('Coded Segments'!$C$2:$C$913,SLR_Covidence_Data_Extraction__66_files[[#This Row],[Study ID_1]],'Coded Segments'!$D$2:$D$913,SLR_Covidence_Data_Extraction__66_files[[#Headers],[Literacy (LIT) > LIT_High]]) -> 0
A7: 27 | B7: X3MHIUD9 | C7: Moorkens 2018 | D7: Translators’ Perceptions of Literary Post-editing using Statistical and Neural Machine Translation | E7: Joss Moorkens | F7: Dublin City University | G7: Ireland | H7: 2018/11/28 | I7: =LEFT(SLR_Covidence_Data_Extraction__66_files[[#This Row],[Publication date]],4) -> 2018 | J7: Netherlands | K7: - To assess Translators' Attitudes: To investigate how professional translators perceive the task of post-editing (PE) specifically when dealing with Neural Machine Translation (NMT) output. - To test NMT Capability in Literature: To evaluate whether a state-of-the-art NMT system can effectively aid in the translation of literary texts - a "long-lifespan" and challenging genre to which machine translation is not traditionally applied. | L7: Questionnaire | O7: Other: Participants translated and post-edited the machine translated selections from the test data using the PET (Post-Editing Tool) interface (Aziz et al. 2012), an open source computer-assisted translation tool for editing at the segment level, built for research purposes. | V7: Online | W7: Offline | Y7: Professional translators who met the following requirements with experience in literary translation. They were native Catalan speakers with professional proficiency in English and had different experience levels. | Z7: Professional translators | AA7: Literary | AB7: 6 | AC7: 6 | AD7: 1. Productivity and Technical Effort (Objective Data) The experiment measured the actual work performed by the six translators under three conditions: from scratch (HT), post-editing Statistical MT (SMT), and post-editing NMT. • Speed Increases: Measurements showed that all translators were faster when post-editing than when translating from scratch. Furthermore, every participant was faster using NMT than SMT. • Reduction in Typing: All translators used fewer keystrokes for NMT compared to SMT. For example, one participant saved 32% in time and 28% in keystrokes when using NMT compared to translating from scratch. • System Performance: NMT was rated higher than SMT across all categories: helpfulness (4/5 vs 3.75/5), fluency (2.75/4 vs 2/4), and adequacy/accuracy (3/4 vs 2.5/4). 2. User Perceptions and Quality Assessment Despite the productivity gains, the translators' subjective views were more critical: • Preference for "From Scratch": Every single participant stated a preference for translating from scratch rather than post-editing. • NMT vs. SMT Quality: Participants agreed that NMT output was more fluent and sounded more natural. In contrast, SMT was criticized for producing "calques" (literal structural copies) of the English source text. • Creative "Priming": A major result was the finding that MT "conditions" or "primes" the translator. Participants felt restricted by the machine's suggestions, leading to more literal translations and a "lack of creativity" compared to their work from scratch. 3. The "Perception vs. Reality" Gap The study highlighted several areas where the translators' feelings did not align with the logged data: • Speed Paradox: While all were objectively faster when post-editing SMT than from scratch, two translators (T1 and T5) perceived themselves to be slower under that condition. • Effort Paradox: Some translators felt that translating from scratch required less effort, even though they actually used more keystrokes for that method than for post-editing. • Resistance to Productivity Gains: Even when shown data proving they were up to 32% faster with NMT, participants maintained their preference for the manual process, arguing that the "freedom" to structure the translation themselves was more valuable than speed. 4. Impact of Experience and Context • The Experience Factor: As noted in our conversation history, there was a divide based on tenure: novice and mid-career translators (less than 10 years’ experience) were more willing to consider post-editing in the future, while the highly experienced experts (25–30 years’ experience) remained firmly opposed to using it. • The Problem of Segmentation: Translators complained that the sentence-level segmentation of the software created a "fragmented vision" of the story, which they described as "translation in the darkness". They argued that literary translation requires a "global view" of paragraphs or pages to maintain the author's style and cultural nuances. | AE7: 1. Productivity Gains do not Equal Professional Preference The study concludes that although technology increases speed, it does not increase job satisfaction. • Objective Speed: All participants were objectively faster when post-editing NMT compared to translating from scratch or using older Statistical MT. • Persistent Resistance: Despite these measured gains (e.g., one participant saved 32% in time), every translator still stated a firm preference for translating "from scratch". • The "Hurry" Use Case: Translators concluded that NMT is only useful as a tool for "hurried" projects or repetitive texts, but it is not something they would choose to use for high-quality creative work. 2. The Creativity and "Priming" Problem A central conclusion is that machine translation interferes with the artistic process of a novel. • Cognitive Conditioning: The researchers found that MT suggestions "prime" or "condition" the translator. This forces the human to work within the machine’s interpretation, leading to more literal translations and a loss of the "freedom" to structure the text creatively. • Literalism vs. Dynamic Equivalence: The study concludes that both MT systems struggled with the "fine details" of literary prose, often producing "calques" (literal structural copies) of the English source rather than a natural Catalan reading experience. 3. The Failure of Segmented Translation The researchers conclude that the standard technological environment for translation is fundamentally unsuited for literature. • "Translation in the Darkness": Participants concluded that sentence-level segmentation creates a "fragmented vision" of the story. • Loss of Context: While humans maintain a "global view" of a page or chapter, the machine provides only a "peephole" view, making it difficult to maintain internal coherence and appropriate cultural nuances (such as correctly assigning gender to a "child" based on earlier context). 4. NMT as the New Technical Standard Technically, the study confirms that NMT is a significant leap forward over Statistical MT (SMT) for creative texts. • Superior Quality: Participants found NMT output to be more fluent and adequate. • Reduced Technical Effort: The move to NMT demonstrated a clear improvement in reducing the number of edits and keystrokes required. 5. Experience and the "Threat" of AI The study concludes that a translator's background significantly shapes their view of the technology: • The Experience Factor: As noted in our conversation history, less-experienced translators found MT suggestions more useful, whereas highly experienced experts (with 25–30 years of tenure) were the most critical and resistant. • Competence Gap: Finally, the researchers conclude that MT is "still far" from being a threat to the profession. They argue that machines currently lack the "extra-linguistic knowledge" and "strategic competence" required to resolve semantic ambiguities and replicate the expert human's ability to create an "equivalent reading experience". | AF7: • Statistical and neural MT systems: The two technological paradigms tested against the traditional method of translating from scratch. • 'Conditioned': A term used to describe how machine suggestions limit a translator's freedom and creativity. • Literal translation / 'Calques': Terms used to characterize the structurally rigid output of MT, particularly Statistical MT, which mimics the source language structure too closely. • Fluent and adequate: The qualitative benchmarks where Neural Machine Translation (NMT) was found to be superior to the older statistical model. • Sentential segmentation: Identified as a primary technical limitation that creates an "awkward" and fragmented work environment for literary professionals. • Extra-linguistic knowledge / competence: A core human skill identified as necessary to resolve semantic ambiguities and create a high-quality literary work. • Equivalent reading experience: The ultimate goal of a literary translator, which the authors conclude NMT is currently unable to replicate independently. • 'Transference': A linguistic term used to describe the machine's act of merely replicating patterns from training data rather than performing true translation. • Strategic competence: A specific professional skill (as defined by the PACTE group) that involves making high-level decisions, which remains a uniquely human advantage. • Human parity: A term referring to claims that machines can match human quality, which the authors explicitly challenge in the context of the literary domain. • Threat: Used to describe the status of MT; the study concludes that while "scary" to some, the technology is "still far" from replacing expert human translators. | AG7: Linguistic challenges; Technical aspects; Ethical aspects | AH7: =+COUNTIFS('Coded Segments'!$C$2:$C$913,SLR_Covidence_Data_Extraction__66_files[[#This Row],[Study ID_1]],'Coded Segments'!$D$2:$D$913,SLR_Covidence_Data_Extraction__66_files[[#Headers],[Adoption (AD) > AD_High]]) -> 0 | AI7: =+COUNTIFS('Coded Segments'!$C$2:$C$913,SLR_Covidence_Data_Extraction__66_files[[#This Row],[Study ID_1]],'Coded Segments'!$D$2:$D$913,SLR_Covidence_Data_Extraction__66_files[[#Headers],[Adoption (AD) > AD_Moderate]]) -> 0 | AJ7: =+COUNTIFS('Coded Segments'!$C$2:$C$913,SLR_Covidence_Data_Extraction__66_files[[#This Row],[Study ID_1]],'Coded Segments'!$D$2:$D$913,SLR_Covidence_Data_Extraction__66_files[[#Headers],[Adoption (AD) > AD_Low]]) -> 1 | AK7: =+COUNTIFS('Coded Segments'!$C$2:$C$913,SLR_Covidence_Data_Extraction__66_files[[#This Row],[Study ID_1]],'Coded Segments'!$D$2:$D$913,SLR_Covidence_Data_Extraction__66_files[[#Headers],[Adoption (AD) > AD_None]]) -> 0 | AL7: =+COUNTIFS('Coded Segments'!$C$2:$C$913,SLR_Covidence_Data_Extraction__66_files[[#This Row],[Study ID_1]],'Coded Segments'!$D$2:$D$913,SLR_Covidence_Data_Extraction__66_files[[#Headers],[Attitude (ATT) > ATT_Negative]]) -> 6 | AM7: =+COUNTIFS('Coded Segments'!$C$2:$C$913,SLR_Covidence_Data_Extraction__66_files[[#This Row],[Study ID_1]],'Coded Segments'!$D$2:$D$913,SLR_Covidence_Data_Extraction__66_files[[#Headers],[Attitude (ATT) > ATT_Positive]]) -> 2 | AN7: =+COUNTIFS('Coded Segments'!$C$2:$C$913,SLR_Covidence_Data_Extraction__66_files[[#This Row],[Study ID_1]],'Coded Segments'!$D$2:$D$913,SLR_Covidence_Data_Extraction__66_files[[#Headers],[Ethical Concerns (EC) > EC_Bias]]) -> 0 | AO7: =+COUNTIFS('Coded Segments'!$C$2:$C$913,SLR_Covidence_Data_Extraction__66_files[[#This Row],[Study ID_1]],'Coded Segments'!$D$2:$D$913,SLR_Covidence_Data_Extraction__66_files[[#Headers],[Ethical Concerns (EC) > EC_Copyright]]) -> 0 | AP7: =+COUNTIFS('Coded Segments'!$C$2:$C$913,SLR_Covidence_Data_Extraction__66_files[[#This Row],[Study ID_1]],'Coded Segments'!$D$2:$D$913,SLR_Covidence_Data_Extraction__66_files[[#Headers],[Ethical Concerns (EC) > EC_Data safety & confidentiality]]) -> 0 | AQ7: =+COUNTIFS('Coded Segments'!$C$2:$C$913,SLR_Covidence_Data_Extraction__66_files[[#This Row],[Study ID_1]],'Coded Segments'!$D$2:$D$913,SLR_Covidence_Data_Extraction__66_files[[#Headers],[Ethical Concerns (EC) > EC_Environmental sustainability]]) -> 0 | AR7: =+COUNTIFS('Coded Segments'!$C$2:$C$913,SLR_Covidence_Data_Extraction__66_files[[#This Row],[Study ID_1]],'Coded Segments'!$D$2:$D$913,SLR_Covidence_Data_Extraction__66_files[[#Headers],[Ethical Concerns (EC) > EC_Payment]]) -> 0 | AS7: =+COUNTIFS('Coded Segments'!$C$2:$C$912,SLR_Covidence_Data_Extraction__66_files[[#This Row],[Study ID_1]],'Coded Segments'!$D$2:$D$912,SLR_Covidence_Data_Extraction__66_files[[#Headers],[Ethical Concerns (EC) > EC_Quality]]) -> 6 | AT7: =+COUNTIFS('Coded Segments'!$C$2:$C$913,SLR_Covidence_Data_Extraction__66_files[[#This Row],[Study ID_1]],'Coded Segments'!$D$2:$D$913,SLR_Covidence_Data_Extraction__66_files[[#Headers],[Ethical Concerns (EC) > EC_Translators’ role & status]]) -> 0 | AU7: =+COUNTIFS('Coded Segments'!$C$2:$C$913,SLR_Covidence_Data_Extraction__66_files[[#This Row],[Study ID_1]],'Coded Segments'!$D$2:$D$913,SLR_Covidence_Data_Extraction__66_files[[#Headers],[Ethical Concerns (EC) > EC_Other]]) -> 0 | AV7: =+COUNTIFS('Coded Segments'!$C$2:$C$913,SLR_Covidence_Data_Extraction__66_files[[#This Row],[Study ID_1]],'Coded Segments'!$D$2:$D$913,SLR_Covidence_Data_Extraction__66_files[[#Headers],[Literacy (LIT) > LIT_Generic]]) -> 0 | AW7: =+COUNTIFS('Coded Segments'!$C$2:$C$913,SLR_Covidence_Data_Extraction__66_files[[#This Row],[Study ID_1]],'Coded Segments'!$D$2:$D$913,SLR_Covidence_Data_Extraction__66_files[[#Headers],[Literacy (LIT) > LIT_None ]]) -> 0 | AX7: =+COUNTIFS('Coded Segments'!$C$2:$C$913,SLR_Covidence_Data_Extraction__66_files[[#This Row],[Study ID_1]],'Coded Segments'!$D$2:$D$913,SLR_Covidence_Data_Extraction__66_files[[#Headers],[Literacy (LIT) > LIT_Low ]]) -> 0 | AY7: =+COUNTIFS('Coded Segments'!$C$2:$C$913,SLR_Covidence_Data_Extraction__66_files[[#This Row],[Study ID_1]],'Coded Segments'!$D$2:$D$913,SLR_Covidence_Data_Extraction__66_files[[#Headers],[Literacy (LIT) > LIT_High]]) -> 0
A8: 34 | B8: 5CEZQLU6 | C8: Courtney 2019 | D8: Translators’ experiences of occupational stress and job satisfaction | E8: Jennifer Courtney E-mail: jennifer.courtney4@mail.dcu.ie | F8: Dublin City University | G8: Ireland | H8: 2019 | I8: =LEFT(SLR_Covidence_Data_Extraction__66_files[[#This Row],[Publication date]],4) -> 2019 | J8: Ireland and UK | K8: To measure the self-perceived occupational stress and job satisfaction levels of translators. | L8: Questionnaire | P8: 5 | Q8: 2 | R8: 7 | S8: 2017/05/24 | T8: 2017/07/19 | U8: Professional associations networks | V8: Online | Y8: Translators who are members of the Chartered Institute of Linguists (UK) or the Irish Translators’ and Interpreters’ Association. | Z8: Professional translators | AA8: General | AB8: 474 | AC8: 474 | AD8: The study found that respondents experience medium to high levels of occupational stress, driven by the following factors: • Time and Speed Pressures: The majority of respondents (63%) reported having to work very fast, and 49% felt pressured to work long hours. • Workload Volatility: Over half (55%) experienced marked increases in workload, often described as a "feast or famine" cycle typical of freelance work. • Psychological Impact: Nearly half of the participants (46%) reported feeling stressed or anxious in the month prior to the survey due to job demands. • Mismatch in Preferences: While many are forced to work under pressure, only 5% of translators actually enjoy doing so, suggesting that job demands often conflict with professional preferences. Paradoxically High Job Satisfaction One of the most significant results is a paradox: despite identifying high stress levels, translators exhibit high to extremely high job satisfaction. • General Satisfaction: Approximately 80% of respondents agreed that, in general, they are satisfied with their job. • Perceived Job Value: Nearly 58% of translators believed it would be difficult for them to find a better job. • Career Commitment: Most respondents (57%) stated they intended to remain in the profession, while 28% would choose a different career if given the option. Thematic Sources of Stress and Satisfaction The qualitative analysis of the survey identified specific drivers behind these feelings: • Major Stressors: These include poor treatment from agencies (feeling undervalued or treated like "robots"), decreasing remuneration, and uncertainty about the future. • The Technology Factor: a portion of respondents (4%) specifically identified machine translation and CAT tools as stressors, noting that technology is "driving down income" and "increasing turnaround times". • Major Satisfiers: Satisfaction is derived from flexibility and autonomy (especially for those who are self-employed) and the "art of translation" itself, which provides mental stimulation and a sense of accomplishment. | AE8: The Stress-Satisfaction Paradox The researchers conclude that there is no established relationship between occupational stress and job satisfaction in the translation profession. While standard organizational psychology often suggests that high stress leads to low satisfaction, this study found the opposite: • High Stress: Translators experience medium to high levels of stress driven by job demands like time pressure and the need to work very fast. • High Satisfaction: Despite these pressures, approximately 80% of respondents are satisfied with their jobs, and most intend to remain in the profession. Sources of Professional Stress The study concludes that the primary stressors for translators are often external and outside their direct control. • Treatment and Remuneration: A major conclusion is that translators feel undervalued and poorly treated by agencies, often being handled like "robots" in an "assembly line". This is compounded by decreasing pay rates and late payments. • Technology as a Stressor: Similar to the Danish and Swiss studies in our conversation history, the sources conclude that machine translation (MT) and CAT tools are significant stressors. Translators feel technology is "driving down income" and "increasing turnaround times," particularly affecting those with many years of experience. • Future Uncertainty: Freelance translators, in particular, suffer from the "feast or famine" cycle, leading to anxiety over the unpredictability of future income and projects. Drivers of Job Satisfaction The study concludes that satisfaction is derived from the intrinsic nature of the work rather than external rewards. • Autonomy and Flexibility: For the freelance majority, the ability to control their own schedule and relocate or spend time with family is a primary source of satisfaction. • The "Art of Translation": Translators find immense fulfillment in the mental stimulation and the craft of producing high-quality texts. Knowing they have "translated something well" provides a sense of accomplishment that outweighs professional stressors. The Power of "Saying No" A key conclusion regarding stress management is that autonomy allows for stress mitigation. Unlike in-house translators, freelancers can choose to reject "unachievable" deadlines or unreasonable projects. The researchers conclude that when stress is "self-imposed" by taking on too much work, translators can improve their well-being by becoming more assertive and learning to decline unsuitable offers. Professional Status and Visibility Finally, the study concludes that translators are highly qualified experts who are very eager to establish their professional credentials. The researchers suggest that the eagerness of respondents to list multiple degrees and honours reflects a desire to combat the low social status and lack of visibility they often feel within the industry. In summary, while translators face a "dark" future regarding industry changes and poor agency treatment, they remain deeply committed to the intellectual and personal independence that the art of translation provides. | AF8: • Occupational stress: The central focus of the study, which was found to be at medium to high levels among the participants. • Job satisfaction: Described as the "cognitive appraisal of the working environment," which the study concluded remains high to immense despite the presence of stressors. • Predictors of occupational stress: The specific external factors identified as the primary causes of stress: poor treatment from agencies and clients, remuneration issues, uncertainty about the future, and tight deadlines. • Self-perceived stress: The study's method of measurement, based on how translators view their own levels of pressure and anxiety. • Self-imposed stress: A conclusion that some stress is not caused by the work itself but by a lack of assertiveness or the translator's inability to "say no" to unreasonable deadlines. • Flexibility and job autonomy: Key sources of satisfaction, particularly for freelancers, involving the ability to negotiate or reject projects and determine one's own working hours. • Art of translation: A source of intrinsic satisfaction derived from the mental stimulation and the act of creating a high-quality new text. • No relationship established: The significant conclusion that, contrary to some literature, high levels of stress in this profession did not result in low levels of job satisfaction. • Highly skilled experts: How translators perceive themselves, contrasted with the conclusion that they often feel undervalued or unrecognised by agencies and the broader industry. • Work-related stress: The broader societal context mentioned in the conclusion, which the authors argue must be addressed to protect the mental and physical health of professionals. • High-pressure society: The modern environment in which the authors conclude it is essential to acknowledge the importance of occupational health. | AG8: Working conditions; Ethical aspects | AH8: =+COUNTIFS('Coded Segments'!$C$2:$C$913,SLR_Covidence_Data_Extraction__66_files[[#This Row],[Study ID_1]],'Coded Segments'!$D$2:$D$913,SLR_Covidence_Data_Extraction__66_files[[#Headers],[Adoption (AD) > AD_High]]) -> 0 | AI8: =+COUNTIFS('Coded Segments'!$C$2:$C$913,SLR_Covidence_Data_Extraction__66_files[[#This Row],[Study ID_1]],'Coded Segments'!$D$2:$D$913,SLR_Covidence_Data_Extraction__66_files[[#Headers],[Adoption (AD) > AD_Moderate]]) -> 0 | AJ8: =+COUNTIFS('Coded Segments'!$C$2:$C$913,SLR_Covidence_Data_Extraction__66_files[[#This Row],[Study ID_1]],'Coded Segments'!$D$2:$D$913,SLR_Covidence_Data_Extraction__66_files[[#Headers],[Adoption (AD) > AD_Low]]) -> 0 | AK8: =+COUNTIFS('Coded Segments'!$C$2:$C$913,SLR_Covidence_Data_Extraction__66_files[[#This Row],[Study ID_1]],'Coded Segments'!$D$2:$D$913,SLR_Covidence_Data_Extraction__66_files[[#Headers],[Adoption (AD) > AD_None]]) -> 0 | AL8: =+COUNTIFS('Coded Segments'!$C$2:$C$913,SLR_Covidence_Data_Extraction__66_files[[#This Row],[Study ID_1]],'Coded Segments'!$D$2:$D$913,SLR_Covidence_Data_Extraction__66_files[[#Headers],[Attitude (ATT) > ATT_Negative]]) -> 4 | AM8: =+COUNTIFS('Coded Segments'!$C$2:$C$913,SLR_Covidence_Data_Extraction__66_files[[#This Row],[Study ID_1]],'Coded Segments'!$D$2:$D$913,SLR_Covidence_Data_Extraction__66_files[[#Headers],[Attitude (ATT) > ATT_Positive]]) -> 4 | AN8: =+COUNTIFS('Coded Segments'!$C$2:$C$913,SLR_Covidence_Data_Extraction__66_files[[#This Row],[Study ID_1]],'Coded Segments'!$D$2:$D$913,SLR_Covidence_Data_Extraction__66_files[[#Headers],[Ethical Concerns (EC) > EC_Bias]]) -> 0 | AO8: =+COUNTIFS('Coded Segments'!$C$2:$C$913,SLR_Covidence_Data_Extraction__66_files[[#This Row],[Study ID_1]],'Coded Segments'!$D$2:$D$913,SLR_Covidence_Data_Extraction__66_files[[#Headers],[Ethical Concerns (EC) > EC_Copyright]]) -> 0 | AP8: =+COUNTIFS('Coded Segments'!$C$2:$C$913,SLR_Covidence_Data_Extraction__66_files[[#This Row],[Study ID_1]],'Coded Segments'!$D$2:$D$913,SLR_Covidence_Data_Extraction__66_files[[#Headers],[Ethical Concerns (EC) > EC_Data safety & confidentiality]]) -> 0 | AQ8: =+COUNTIFS('Coded Segments'!$C$2:$C$913,SLR_Covidence_Data_Extraction__66_files[[#This Row],[Study ID_1]],'Coded Segments'!$D$2:$D$913,SLR_Covidence_Data_Extraction__66_files[[#Headers],[Ethical Concerns (EC) > EC_Environmental sustainability]]) -> 0 | AR8: =+COUNTIFS('Coded Segments'!$C$2:$C$913,SLR_Covidence_Data_Extraction__66_files[[#This Row],[Study ID_1]],'Coded Segments'!$D$2:$D$913,SLR_Covidence_Data_Extraction__66_files[[#Headers],[Ethical Concerns (EC) > EC_Payment]]) -> 2 | AS8: =+COUNTIFS('Coded Segments'!$C$2:$C$912,SLR_Covidence_Data_Extraction__66_files[[#This Row],[Study ID_1]],'Coded Segments'!$D$2:$D$912,SLR_Covidence_Data_Extraction__66_files[[#Headers],[Ethical Concerns (EC) > EC_Quality]]) -> 0 | AT8: =+COUNTIFS('Coded Segments'!$C$2:$C$913,SLR_Covidence_Data_Extraction__66_files[[#This Row],[Study ID_1]],'Coded Segments'!$D$2:$D$913,SLR_Covidence_Data_Extraction__66_files[[#Headers],[Ethical Concerns (EC) > EC_Translators’ role & status]]) -> 0 | AU8: =+COUNTIFS('Coded Segments'!$C$2:$C$913,SLR_Covidence_Data_Extraction__66_files[[#This Row],[Study ID_1]],'Coded Segments'!$D$2:$D$913,SLR_Covidence_Data_Extraction__66_files[[#Headers],[Ethical Concerns (EC) > EC_Other]]) -> 0 | AV8: =+COUNTIFS('Coded Segments'!$C$2:$C$913,SLR_Covidence_Data_Extraction__66_files[[#This Row],[Study ID_1]],'Coded Segments'!$D$2:$D$913,SLR_Covidence_Data_Extraction__66_files[[#Headers],[Literacy (LIT) > LIT_Generic]]) -> 0 | AW8: =+COUNTIFS('Coded Segments'!$C$2:$C$913,SLR_Covidence_Data_Extraction__66_files[[#This Row],[Study ID_1]],'Coded Segments'!$D$2:$D$913,SLR_Covidence_Data_Extraction__66_files[[#Headers],[Literacy (LIT) > LIT_None ]]) -> 0 | AX8: =+COUNTIFS('Coded Segments'!$C$2:$C$913,SLR_Covidence_Data_Extraction__66_files[[#This Row],[Study ID_1]],'Coded Segments'!$D$2:$D$913,SLR_Covidence_Data_Extraction__66_files[[#Headers],[Literacy (LIT) > LIT_Low ]]) -> 0 | AY8: =+COUNTIFS('Coded Segments'!$C$2:$C$913,SLR_Covidence_Data_Extraction__66_files[[#This Row],[Study ID_1]],'Coded Segments'!$D$2:$D$913,SLR_Covidence_Data_Extraction__66_files[[#Headers],[Literacy (LIT) > LIT_High]]) -> 0
A9: 8 | B9: A4JRPBMU | C9: Beikian 2019 | D9: Translation Technology Tools and Professional Translators’ Attitudes toward Them | E9: Ali Beikian E-mail: a_beikian@yahoo.co.uk | F9: PhD Candidate, University of Isfahan, Isfahan, Iran | G9: Iran | H9: 2019/03 | I9: =LEFT(SLR_Covidence_Data_Extraction__66_files[[#This Row],[Publication date]],4) -> 2019 | J9: Iran | K9: The present two-phase study seeks to shed some light on what translation technology tools are and how professional translators feel toward them. | L9: Questionnaire | P9: 34 | Q9: 0 | R9: 34 | U9: Other: ProZ.com quick polls | V9: Online | Y9: ProZ.com members | Z9: Professional translators | AA9: General | AD9: General Technology and Internet Reliance • Positive Sentiment: A significant portion of respondents (29.30%) claim to "just love" technology, while 34.20% describe a "love-hate" relationship. Only 3.80% reported that they "just hate" it. • Internet Necessity: The community is highly dependent on digital connectivity; 75.50% cannot imagine their life as a translator without the internet, and 81.40% work exclusively via the internet. CAT Tool Impact • Usage and Career: 65.6% of translators use CAT tools on a regular basis. 74% of respondents believe using these tools increases work opportunities, and 39.4% reported an increase in income due to their adoption. • Productivity vs. Quality: While 46.5% are certain that CAT tools increase their translation output, the results regarding quality are more sceptical. A majority (56.2%) believe CAT tools do not necessarily improve the quality of translations. • Ease of Learning: The study found that CAT tools are relatively accessible, with 36% of translators learning to use them in less than a week. Machine Translation (MT) Perceptions The results regarding MT were more conservative compared to general technology or CAT tools: • Usage: Over half (55.90%) of the respondents do not use MT. • Job Security: Despite the rise of automation, 69% of respondents believe MT will never replace human translators, and 66% do not feel threatened by the technology. • Professional Stance: MT is the only category where a plurality (42.80%) views the technology as a "foe" rather than a friend. | AE9: The Root of Technological Friction The authors conclude that the primary reason some translators, scholars, and clients "fail to get along" with translation technology is ill-informedness. They argue that many negative perceptions are rooted in a lack of understanding regarding the purposes, capabilities, and specific limitations of various tools. When these tools are misunderstood, clients may have unrealistic expectations for price and speed, while translators may view the technology with unnecessary hostility. Positive Professional Sentiment Contrary to the narrative that many translators "hate" technology, the study concludes that most professionals have a positive relationship with it. • Adoption and Affect: Most translators either "love" technology or do not experience a "love-hate" relationship, using it to support the entire translation workflow from marketing to final delivery. • Enabling, Not Replacing: The researchers concluded that translation tools are aids to human translators rather than replacements for them. They found that using technology often makes the translation process more enjoyable and fulfilling. Strategic Professional Benefits The study concludes that the integration of technology is essential for modern professional practice for several reasons: • Meeting Market Demands: Technology allows translators to meet or exceed ever-growing client demands for speed and productivity. • Handling Complexity: Tools like CAT software are vital for managing "thorny" or "fiddly" file types common in desktop publishing (DTP), localization, and audiovisual projects. • Quality and Consistency: The use of Translation Memory (TM) and Quality Assurance (QA) tools helps professionals maintain consistency in terminology and style while catching common errors. The Role of Machine Translation (MT) Regarding the more controversial area of MT, the study concludes that even this technology can be viewed as an advantage: • Market Expansion: Free online translation has enabled businesses to make more international connections, ultimately creating more potential customers for professional translators. • Recognition of Human Value: Businesses that experiment with MT often quickly recognise its limitations, which reinforces the conclusion that human translation is necessary for critical business communications. Ultimately, the study serves as a foundational call for further, more conclusive research to bridge the gap between technological advancement and professional uptake | AF9: • Ill-informedness: Identified by the authors as the most significant reason why some translators and technology "do not always get along", referring specifically to a lack of knowledge regarding the nature and purposes of these tools. • Exploratory study: The classification of the research, which aims to provide a starting point for more conclusive and detailed investigations in the future. • Aids to human translators: A primary conclusion stating that technology tools are intended to assist professionals rather than replace them. • Love-hate relationship: A phrase used to describe the emotional dynamic with technology; the study concludes that most translators either do not experience this conflict or simply "love" the technology. • Clients’ ever-growing demands: The external market pressures that translators are able to meet, and even exceed, through the use of technology. • Applications, capabilities, and limitations: The three areas regarding technology tools that the authors conclude must be understood to prevent professional friction. • Enjoyable translation: A term used to describe the ideal professional state achieved when technology is used to facilitate and improve the quality of work. • Translation studies researchers and scholars: The specific audience the authors hope to motivate to expand research into the technologisation of the craft. | AG9: Technical aspects; Training needs; Ethical aspects | AH9: =+COUNTIFS('Coded Segments'!$C$2:$C$913,SLR_Covidence_Data_Extraction__66_files[[#This Row],[Study ID_1]],'Coded Segments'!$D$2:$D$913,SLR_Covidence_Data_Extraction__66_files[[#Headers],[Adoption (AD) > AD_High]]) -> 0 | AI9: =+COUNTIFS('Coded Segments'!$C$2:$C$913,SLR_Covidence_Data_Extraction__66_files[[#This Row],[Study ID_1]],'Coded Segments'!$D$2:$D$913,SLR_Covidence_Data_Extraction__66_files[[#Headers],[Adoption (AD) > AD_Moderate]]) -> 0 | AJ9: =+COUNTIFS('Coded Segments'!$C$2:$C$913,SLR_Covidence_Data_Extraction__66_files[[#This Row],[Study ID_1]],'Coded Segments'!$D$2:$D$913,SLR_Covidence_Data_Extraction__66_files[[#Headers],[Adoption (AD) > AD_Low]]) -> 1 | AK9: =+COUNTIFS('Coded Segments'!$C$2:$C$913,SLR_Covidence_Data_Extraction__66_files[[#This Row],[Study ID_1]],'Coded Segments'!$D$2:$D$913,SLR_Covidence_Data_Extraction__66_files[[#Headers],[Adoption (AD) > AD_None]]) -> 0 | AL9: =+COUNTIFS('Coded Segments'!$C$2:$C$913,SLR_Covidence_Data_Extraction__66_files[[#This Row],[Study ID_1]],'Coded Segments'!$D$2:$D$913,SLR_Covidence_Data_Extraction__66_files[[#Headers],[Attitude (ATT) > ATT_Negative]]) -> 2 | AM9: =+COUNTIFS('Coded Segments'!$C$2:$C$913,SLR_Covidence_Data_Extraction__66_files[[#This Row],[Study ID_1]],'Coded Segments'!$D$2:$D$913,SLR_Covidence_Data_Extraction__66_files[[#Headers],[Attitude (ATT) > ATT_Positive]]) -> 5 | AN9: =+COUNTIFS('Coded Segments'!$C$2:$C$913,SLR_Covidence_Data_Extraction__66_files[[#This Row],[Study ID_1]],'Coded Segments'!$D$2:$D$913,SLR_Covidence_Data_Extraction__66_files[[#Headers],[Ethical Concerns (EC) > EC_Bias]]) -> 0 | AO9: =+COUNTIFS('Coded Segments'!$C$2:$C$913,SLR_Covidence_Data_Extraction__66_files[[#This Row],[Study ID_1]],'Coded Segments'!$D$2:$D$913,SLR_Covidence_Data_Extraction__66_files[[#Headers],[Ethical Concerns (EC) > EC_Copyright]]) -> 0 | AP9: =+COUNTIFS('Coded Segments'!$C$2:$C$913,SLR_Covidence_Data_Extraction__66_files[[#This Row],[Study ID_1]],'Coded Segments'!$D$2:$D$913,SLR_Covidence_Data_Extraction__66_files[[#Headers],[Ethical Concerns (EC) > EC_Data safety & confidentiality]]) -> 0 | AQ9: =+COUNTIFS('Coded Segments'!$C$2:$C$913,SLR_Covidence_Data_Extraction__66_files[[#This Row],[Study ID_1]],'Coded Segments'!$D$2:$D$913,SLR_Covidence_Data_Extraction__66_files[[#Headers],[Ethical Concerns (EC) > EC_Environmental sustainability]]) -> 0 | AR9: =+COUNTIFS('Coded Segments'!$C$2:$C$913,SLR_Covidence_Data_Extraction__66_files[[#This Row],[Study ID_1]],'Coded Segments'!$D$2:$D$913,SLR_Covidence_Data_Extraction__66_files[[#Headers],[Ethical Concerns (EC) > EC_Payment]]) -> 0 | AS9: =+COUNTIFS('Coded Segments'!$C$2:$C$912,SLR_Covidence_Data_Extraction__66_files[[#This Row],[Study ID_1]],'Coded Segments'!$D$2:$D$912,SLR_Covidence_Data_Extraction__66_files[[#Headers],[Ethical Concerns (EC) > EC_Quality]]) -> 0 | AT9: =+COUNTIFS('Coded Segments'!$C$2:$C$913,SLR_Covidence_Data_Extraction__66_files[[#This Row],[Study ID_1]],'Coded Segments'!$D$2:$D$913,SLR_Covidence_Data_Extraction__66_files[[#Headers],[Ethical Concerns (EC) > EC_Translators’ role & status]]) -> 1 | AU9: =+COUNTIFS('Coded Segments'!$C$2:$C$913,SLR_Covidence_Data_Extraction__66_files[[#This Row],[Study ID_1]],'Coded Segments'!$D$2:$D$913,SLR_Covidence_Data_Extraction__66_files[[#Headers],[Ethical Concerns (EC) > EC_Other]]) -> 0 | AV9: =+COUNTIFS('Coded Segments'!$C$2:$C$913,SLR_Covidence_Data_Extraction__66_files[[#This Row],[Study ID_1]],'Coded Segments'!$D$2:$D$913,SLR_Covidence_Data_Extraction__66_files[[#Headers],[Literacy (LIT) > LIT_Generic]]) -> 0 | AW9: =+COUNTIFS('Coded Segments'!$C$2:$C$913,SLR_Covidence_Data_Extraction__66_files[[#This Row],[Study ID_1]],'Coded Segments'!$D$2:$D$913,SLR_Covidence_Data_Extraction__66_files[[#Headers],[Literacy (LIT) > LIT_None ]]) -> 1 | AX9: =+COUNTIFS('Coded Segments'!$C$2:$C$913,SLR_Covidence_Data_Extraction__66_files[[#This Row],[Study ID_1]],'Coded Segments'!$D$2:$D$913,SLR_Covidence_Data_Extraction__66_files[[#Headers],[Literacy (LIT) > LIT_Low ]]) -> 0 | AY9: =+COUNTIFS('Coded Segments'!$C$2:$C$913,SLR_Covidence_Data_Extraction__66_files[[#This Row],[Study ID_1]],'Coded Segments'!$D$2:$D$913,SLR_Covidence_Data_Extraction__66_files[[#Headers],[Literacy (LIT) > LIT_High]]) -> 0
A10: 25 | B10: IU5G3Y6L | C10: Lesznyák 2019 | D10: Hungarian translators’ perceptions of neural machine translation in the European Commission | E10: Ágnes Lesznyák E-mail: agnes.lesznyak@ec.europa.eu | F10: European Commission Directorate-General for Translation | G10: Europe | H10: 2019/08 | I10: =LEFT(SLR_Covidence_Data_Extraction__66_files[[#This Row],[Publication date]],4) -> 2019 | J10: Hungary | K10: To explore the views, work practices, and practical experiences of professional Hungarian translators regarding Neural Machine Translation (NMT) within the European Commission’s Directorate-General for Translation (DGT). | N10: Interviews | S10: 2018/06 | T10: 2019/01 | U10: Other: DGT’s Hungarian Language Department | W10: Offline | Y10: Translators working in DGT’s Hungarian Language Department | Z10: Professional translators | AA10: Legal | AB10: 38 | AC10: 38 | AD10: 1. The "Deceptive Fluency" and Quality Paradox • Segment Length Correlation: Translators found a direct link between segment length and NMT quality. Short segments (under 30–40 words) are generally of high quality and only need revision, whereas long segments are often so poor they must be deleted and re-translated from scratch. • Fluency vs. Accuracy: The two most critical issues identified were mistranslation and deceptive fluency. Translators reported being "deceived" by the linguistic smoothness of the Hungarian output, which can mask serious errors in word order, misplaced attributes, or the inversion of subject and object. • Terminology and Proper Names: Translators noted a high risk in legal texts due to incorrect or inconsistent terminology. A unique recurring error in Hungarian NMT is the translation of proper names into "fictional words," which poses a significant risk for document clarity. 2. Integration into Work Practices • The Rejection of "Post-Editing": Interestingly, many translators do not post-edit in the traditional sense. To avoid being misled by the machine's fluency, they instead insert "chunks" or re-type solutions into their own mental structures to maintain professional control. • Reading Strategies: The majority of translators (42%) choose to read the source sentence first. They argue this prevents them from being "trapped" or influenced by a wrong MT rendering before they have formed their own understanding of the segment. • Relevance to TMs: Translators prioritize consistency with previous legal bases. They often rely on "match rates" and only import NMT files if the retrieval from existing translation memories (TMs) is under 30% or 50%. 3. Professional and Psychological Impact • Speed and Effort: Results regarding productivity were split; half reported that NMT speeds up their work and reduces typing effort, while the other half were unsure or felt it simply shifted the burden to the revision stage. • Psychological Benefits: A quarter of participants found it reassuring to have a segment that was not blank, using the MT as a "source of inspiration" when tired. • The "Creativity" Risk: Some translators complained that the tool was "killing creativity" by forcing them into a passive role of "cleaning up" text rather than actively creating it. 4. Impact on the Revision Phase • Transparency: Nearly all revisers (35 out of 38) stated they could clearly recognize when NMT had been used, even if not signaled by the software. • Increased Workload: Several reported that pre-revision translations have become of lower quality since the introduction of NMT, requiring more intervention and effort from revisers and sometimes leading to inter-collegial tension. | AE10: 1. Primacy of Human Factors A central conclusion is that human factors play a crucial role in how technology is successfully applied. The study argues that to understand the adoption of NMT, researchers must pay greater attention to translators' attitudes, agency, and cognitive processes rather than just focusing on technical output or productivity metrics. 2. Control vs. Automation The study concludes that translators have a strong professional need to remain "in control" of the final outcome. • Translating instead of Post-editing: Because they view traditional post-editing (PE) as a high-risk activity that can "deceive" them with its fluency, many translators have developed working methods where they actively translate—using NMT only as a reference or source of "chunks"—rather than simply cleaning up the machine's output. • Compensatory Strategies: These methods are designed to compensate for the unpredictable quality of NMT, which varies greatly from segment to segment and cannot be reliably predicted. 3. The Shift in Quality Risks The research identifies a significant conclusion regarding the revision stage of the workflow: • Pressure on Revisers: Because some translators use NMT as a "source of inspiration" or to speed up their work without thorough checking, some errors are filtering through to the final phase. • Lower Pre-revision Quality: This has led to a perception among revisers that pre-revision translations are of lower quality than before NMT was introduced, requiring more effort and sometimes causing inter-collegial tension. 4. Psychological and Professional Awareness Finally, the study concludes that the introduction of NMT has acted as a catalyst for professional reflection: • Conflicting Views: The highly divergent and sometimes conflicting views among translators may not be new, but the need to adapt to a new tool has made existing differences in professional philosophy more apparent. • Creativity and Motivation: There is an ongoing risk that NMT could drive translators into a passive role, potentially "killing creativity" and affecting long-term translation skills if not addressed through better quality management and motivation strategies. | AF10: • Neural Machine Translation (NMT): The specific technological "translation aid" being evaluated throughout the study. • Substitute for human translation: The conclusion explicitly states that despite its benefits, NMT is not a replacement for human expertise. • Translate rather than post-edit: This phrase describes the primary compensatory strategy used by translators to maintain control over the final product. • Unpredictable quality: Highlights the core challenge of NMT, where output varies "greatly from segment to segment" and cannot be reliably anticipated. • Pressure on revisers: Refers to the increased workload and quality assurance risks that occur when uncorrected NMT errors filter through to the final phase of the workflow. • Conflicting views: Used to describe the "wide range" of often contradictory opinions held by professionals regarding the tool's usefulness. • Reflection on new circumstances: Suggests that the introduction of NMT has forced translators to become more aware of their own professional philosophies and methods. | AG10: Linguistic challenges; Technical aspects; Working conditions; Ethical aspects | AH10: =+COUNTIFS('Coded Segments'!$C$2:$C$913,SLR_Covidence_Data_Extraction__66_files[[#This Row],[Study ID_1]],'Coded Segments'!$D$2:$D$913,SLR_Covidence_Data_Extraction__66_files[[#Headers],[Adoption (AD) > AD_High]]) -> 1 | AI10: =+COUNTIFS('Coded Segments'!$C$2:$C$913,SLR_Covidence_Data_Extraction__66_files[[#This Row],[Study ID_1]],'Coded Segments'!$D$2:$D$913,SLR_Covidence_Data_Extraction__66_files[[#Headers],[Adoption (AD) > AD_Moderate]]) -> 0 | AJ10: =+COUNTIFS('Coded Segments'!$C$2:$C$913,SLR_Covidence_Data_Extraction__66_files[[#This Row],[Study ID_1]],'Coded Segments'!$D$2:$D$913,SLR_Covidence_Data_Extraction__66_files[[#Headers],[Adoption (AD) > AD_Low]]) -> 0 | AK10: =+COUNTIFS('Coded Segments'!$C$2:$C$913,SLR_Covidence_Data_Extraction__66_files[[#This Row],[Study ID_1]],'Coded Segments'!$D$2:$D$913,SLR_Covidence_Data_Extraction__66_files[[#Headers],[Adoption (AD) > AD_None]]) -> 0 | AL10: =+COUNTIFS('Coded Segments'!$C$2:$C$913,SLR_Covidence_Data_Extraction__66_files[[#This Row],[Study ID_1]],'Coded Segments'!$D$2:$D$913,SLR_Covidence_Data_Extraction__66_files[[#Headers],[Attitude (ATT) > ATT_Negative]]) -> 6 | AM10: =+COUNTIFS('Coded Segments'!$C$2:$C$913,SLR_Covidence_Data_Extraction__66_files[[#This Row],[Study ID_1]],'Coded Segments'!$D$2:$D$913,SLR_Covidence_Data_Extraction__66_files[[#Headers],[Attitude (ATT) > ATT_Positive]]) -> 1 | AN10: =+COUNTIFS('Coded Segments'!$C$2:$C$913,SLR_Covidence_Data_Extraction__66_files[[#This Row],[Study ID_1]],'Coded Segments'!$D$2:$D$913,SLR_Covidence_Data_Extraction__66_files[[#Headers],[Ethical Concerns (EC) > EC_Bias]]) -> 0 | AO10: =+COUNTIFS('Coded Segments'!$C$2:$C$913,SLR_Covidence_Data_Extraction__66_files[[#This Row],[Study ID_1]],'Coded Segments'!$D$2:$D$913,SLR_Covidence_Data_Extraction__66_files[[#Headers],[Ethical Concerns (EC) > EC_Copyright]]) -> 0 | AP10: =+COUNTIFS('Coded Segments'!$C$2:$C$913,SLR_Covidence_Data_Extraction__66_files[[#This Row],[Study ID_1]],'Coded Segments'!$D$2:$D$913,SLR_Covidence_Data_Extraction__66_files[[#Headers],[Ethical Concerns (EC) > EC_Data safety & confidentiality]]) -> 0 | AQ10: =+COUNTIFS('Coded Segments'!$C$2:$C$913,SLR_Covidence_Data_Extraction__66_files[[#This Row],[Study ID_1]],'Coded Segments'!$D$2:$D$913,SLR_Covidence_Data_Extraction__66_files[[#Headers],[Ethical Concerns (EC) > EC_Environmental sustainability]]) -> 0 | AR10: =+COUNTIFS('Coded Segments'!$C$2:$C$913,SLR_Covidence_Data_Extraction__66_files[[#This Row],[Study ID_1]],'Coded Segments'!$D$2:$D$913,SLR_Covidence_Data_Extraction__66_files[[#Headers],[Ethical Concerns (EC) > EC_Payment]]) -> 0 | AS10: =+COUNTIFS('Coded Segments'!$C$2:$C$912,SLR_Covidence_Data_Extraction__66_files[[#This Row],[Study ID_1]],'Coded Segments'!$D$2:$D$912,SLR_Covidence_Data_Extraction__66_files[[#Headers],[Ethical Concerns (EC) > EC_Quality]]) -> 6 | AT10: =+COUNTIFS('Coded Segments'!$C$2:$C$913,SLR_Covidence_Data_Extraction__66_files[[#This Row],[Study ID_1]],'Coded Segments'!$D$2:$D$913,SLR_Covidence_Data_Extraction__66_files[[#Headers],[Ethical Concerns (EC) > EC_Translators’ role & status]]) -> 0 | AU10: =+COUNTIFS('Coded Segments'!$C$2:$C$913,SLR_Covidence_Data_Extraction__66_files[[#This Row],[Study ID_1]],'Coded Segments'!$D$2:$D$913,SLR_Covidence_Data_Extraction__66_files[[#Headers],[Ethical Concerns (EC) > EC_Other]]) -> 0 | AV10: =+COUNTIFS('Coded Segments'!$C$2:$C$913,SLR_Covidence_Data_Extraction__66_files[[#This Row],[Study ID_1]],'Coded Segments'!$D$2:$D$913,SLR_Covidence_Data_Extraction__66_files[[#Headers],[Literacy (LIT) > LIT_Generic]]) -> 0 | AW10: =+COUNTIFS('Coded Segments'!$C$2:$C$913,SLR_Covidence_Data_Extraction__66_files[[#This Row],[Study ID_1]],'Coded Segments'!$D$2:$D$913,SLR_Covidence_Data_Extraction__66_files[[#Headers],[Literacy (LIT) > LIT_None ]]) -> 0 | AX10: =+COUNTIFS('Coded Segments'!$C$2:$C$913,SLR_Covidence_Data_Extraction__66_files[[#This Row],[Study ID_1]],'Coded Segments'!$D$2:$D$913,SLR_Covidence_Data_Extraction__66_files[[#Headers],[Literacy (LIT) > LIT_Low ]]) -> 0 | AY10: =+COUNTIFS('Coded Segments'!$C$2:$C$913,SLR_Covidence_Data_Extraction__66_files[[#This Row],[Study ID_1]],'Coded Segments'!$D$2:$D$913,SLR_Covidence_Data_Extraction__66_files[[#Headers],[Literacy (LIT) > LIT_High]]) -> 0
A11: 30 | B11: KWPKC6YJ | C11: Kerremans 2019 | D11: TECHNOLOGY USE BY PUBLIC SERVICE INTERPRETERS AND TRANSLATORS: THE LINK BETWEEN FREQUENCY OF USE AND FORMS OF PRIOR TRAINING | E11: Koen Kerremans E-mail: koen.kerremans@vub.be | F11: Vrije Universiteit Brussel, Belgium | G11: Belgium | H11: 2019/04/30 | I11: =LEFT(SLR_Covidence_Data_Extraction__66_files[[#This Row],[Publication date]],4) -> 2019 | J11: Worldwide | K11: To obtain information about public service interpreters and translators use of technology as a possible bridging instrument for communication in public services | L11: Questionnaire | S11: 2018/03 | T11: 2018/09 | U11: Professional associations networks | V11: Online | Y11: Public service interpreters and translators | Z11: Professional translators | AA11: General | AB11: 188 | AC11: 188 | AD11: 1. Frequency of Technology Use The researchers found an overall low frequency of use for specialised technologies across the PSIT sector. The findings for specific categories are as follows: • CAT and TB Tools: A vast majority of respondents are unfamiliar with these tools. 73.4% do not use Computer-Assisted Translation (CAT), and 81.4% do not use Termbase Management (TB) systems. In fact, nearly half of the respondents reported not even knowing what these technologies were. • IM, MT, and VC: These are used more extensively, though still by fewer than half of the participants. Instant Messaging (IM) had the highest "very frequent" use at 28.2%, followed by Machine Translation (MT) at 17.6%, and Video Conferencing (VC) at 8%. • Correlations: There are weak positive correlations between the use of different tools, suggesting that a professional who adopts one form of technology is slightly more likely to use others. 2. Impact of Prior Training The study highlights a significant gap between professional practice and formal education: • Forms of Learning: Only 10% to 18% of respondents learned to use these technologies during their university studies. Instead, self-training is the most common method for learning IM (60%), MT (58%), and VC (50%). • Formal Translation/Interpreting Training: Participants with formal higher education in translation or interpreting showed significantly higher use of CAT tools compared to those without, though usage remained low overall. • Specific PSIT Training: Completing a course specifically dedicated to public service interpreting and translation was found to lead to a significantly higher frequency of MT use. • Self-Training Efficacy: For Termbase (TB) systems, self-training was associated with a significantly higher frequency of use than informal training or workshops. 3. Demographic and Geographical Variations • Age: Age generally does not correlate with technology use, with one exception: there is a weak negative correlation regarding MT, suggesting that younger PSITs use machine translation more frequently than their older colleagues. • Time Spent on PSIT: Surprisingly, professionals who spend more than 50% of their time on PSIT activities do not use technology more than those who do it less frequently. This may be because those with lower PSIT workloads are active in other translation fields where technology is more established. • Geography: European PSITs use CAT and TB tools significantly more than their Australian peers. This is likely due to European curricula integrating these tools more frequently into formal training. 4. Professional Motivations and Barriers The study provides qualitative insights into why PSITs choose or reject certain tools: • Reasons for Non-Use: Many respondents view CAT tools as unnecessary for interpreting or for short translation projects without repetition. Regarding Video Conferencing, some interpreters expressed concerns that it makes the service "impersonal" and could lead to a decrease in pay and professional status compared to onsite work. • Reasons for Adoption: Those who use technology do so to save time, improve quality, and ensure terminology consistency. IM is primarily used for rapid communication with agencies and colleagues rather than for the translation task itself. • Security Concerns: A notable barrier to using Instant Messaging and Machine Translation is the perception of confidentiality and reliability issues, which some participants feel are unprofessional in a public service context. | AE11: General Low Adoption and Unfamiliarity The researchers conclude that there is an overall low frequency of technology use across the PSIT sector. A striking finding is that a vast majority of respondents are entirely unfamiliar with established tools like Computer-Assisted Translation (CAT) and Termbase Management (TB) systems; nearly half of the participants reported not even knowing what these technologies were. This suggests that technologies considered standard in the broader translation industry have not yet become essential in the PSIT workflow. The Role and Limitations of Training A primary conclusion of the study is that formal university education currently plays a minor role in technological literacy for PSITs. • Only 10% to 18% of respondents learnt to use these technologies during their formal studies. • Self-training is the most common method for acquiring skills in Instant Messaging (IM), Machine Translation (MT), and Video Conferencing (VC). • While formal translator training does positively influence the frequency of CAT tool use, the overall usage remains very low regardless of background. • Specific PSIT training is a determining factor for the use of Machine Translation, suggesting that specialized courses can encourage the adoption of certain tools. Geographical and Curricular Differences The authors conclude that geographical location significantly impacts tool adoption. European PSITs use CAT and TB tools more readily than their Australian counterparts. The study attributes this to the fact that European translation and interpreting programmes tend to integrate technological training more consistently into their curricula. Professional and Perceptual Barriers The researchers identify several qualitative reasons why PSITs resist certain technologies: • Interpreting vs. Translation: Many PSITs view CAT tools as irrelevant for interpreting or for short, non-repetitive translation tasks. • Professional Status and Quality: There is a significant concern, particularly regarding Video Conferencing, that technology makes the service "impersonal". Interpreters fear that remote technology could lead to a decrease in pay and professional status while causing service quality to "plummet" due to the loss of nuanced meaning transfer. • Security and Professionalism: Barriers to using IM and MT include concerns over confidentiality and the perception that using such tools with clients is unprofessional. Future Research Directions The study concludes that the PSIT profession is at a crossroads where technological competencies are gaining ground but are not yet fully realized. The authors suggest that future research must better distinguish between the needs of interpreters versus translators and explore how technology can be effectively deployed in the highly specific, high-stakes environments of public service provision. | AF11: • Prior forms of technology training: The central variable explored in the conclusion to determine if educational background relates to professional tool adoption. • Frequency of use: The metric used to measure how often PSITs deploy specific technologies in their work. • Determining factor: A term used to describe the role that the nature of the training method may play in whether a professional adopts a specific technology. • Subjective claims: A methodological term used to acknowledge a limitation of the study, as the data measures what respondents say they do rather than observed behaviour. • Misconceptions: Refers to instances where respondents interpreted questions differently than intended, such as confusing termbase (TB) management tools with general internet searches. • Subgroups (Public service interpreters vs. public service translators): A critical distinction identified in the conclusion; the authors note that failing to separate these roles may distort the view of technology use since the tasks are fundamentally different. • Professional contexts: The specific work environments of individual respondents, which the authors conclude must be explored more deeply to understand technology adoption. • Work regime (Employee vs. freelancer): A professional status category that the researchers identify as a potential influence on how frequently a linguist uses technology. • Attitudes towards technology: A psychological factor identified as a necessary pathway for future research to complement data on usage frequency. • Languages of lesser diffusion: A term for languages that have fewer digital resources or tools available, which the authors conclude may limit a professional's ability to use certain technologies. • Bridging instruments: Though used throughout, this term appears in the conclusion to define the role technology plays in facilitating communication within multilingual service provision. | AG11: Technical aspects; Training needs; Working conditions | AH11: =+COUNTIFS('Coded Segments'!$C$2:$C$913,SLR_Covidence_Data_Extraction__66_files[[#This Row],[Study ID_1]],'Coded Segments'!$D$2:$D$913,SLR_Covidence_Data_Extraction__66_files[[#Headers],[Adoption (AD) > AD_High]]) -> 0 | AI11: =+COUNTIFS('Coded Segments'!$C$2:$C$913,SLR_Covidence_Data_Extraction__66_files[[#This Row],[Study ID_1]],'Coded Segments'!$D$2:$D$913,SLR_Covidence_Data_Extraction__66_files[[#Headers],[Adoption (AD) > AD_Moderate]]) -> 0 | AJ11: =+COUNTIFS('Coded Segments'!$C$2:$C$913,SLR_Covidence_Data_Extraction__66_files[[#This Row],[Study ID_1]],'Coded Segments'!$D$2:$D$913,SLR_Covidence_Data_Extraction__66_files[[#Headers],[Adoption (AD) > AD_Low]]) -> 1 | AK11: =+COUNTIFS('Coded Segments'!$C$2:$C$913,SLR_Covidence_Data_Extraction__66_files[[#This Row],[Study ID_1]],'Coded Segments'!$D$2:$D$913,SLR_Covidence_Data_Extraction__66_files[[#Headers],[Adoption (AD) > AD_None]]) -> 0 | AL11: =+COUNTIFS('Coded Segments'!$C$2:$C$913,SLR_Covidence_Data_Extraction__66_files[[#This Row],[Study ID_1]],'Coded Segments'!$D$2:$D$913,SLR_Covidence_Data_Extraction__66_files[[#Headers],[Attitude (ATT) > ATT_Negative]]) -> 2 | AM11: =+COUNTIFS('Coded Segments'!$C$2:$C$913,SLR_Covidence_Data_Extraction__66_files[[#This Row],[Study ID_1]],'Coded Segments'!$D$2:$D$913,SLR_Covidence_Data_Extraction__66_files[[#Headers],[Attitude (ATT) > ATT_Positive]]) -> 0 | AN11: =+COUNTIFS('Coded Segments'!$C$2:$C$913,SLR_Covidence_Data_Extraction__66_files[[#This Row],[Study ID_1]],'Coded Segments'!$D$2:$D$913,SLR_Covidence_Data_Extraction__66_files[[#Headers],[Ethical Concerns (EC) > EC_Bias]]) -> 0 | AO11: =+COUNTIFS('Coded Segments'!$C$2:$C$913,SLR_Covidence_Data_Extraction__66_files[[#This Row],[Study ID_1]],'Coded Segments'!$D$2:$D$913,SLR_Covidence_Data_Extraction__66_files[[#Headers],[Ethical Concerns (EC) > EC_Copyright]]) -> 0 | AP11: =+COUNTIFS('Coded Segments'!$C$2:$C$913,SLR_Covidence_Data_Extraction__66_files[[#This Row],[Study ID_1]],'Coded Segments'!$D$2:$D$913,SLR_Covidence_Data_Extraction__66_files[[#Headers],[Ethical Concerns (EC) > EC_Data safety & confidentiality]]) -> 2 | AQ11: =+COUNTIFS('Coded Segments'!$C$2:$C$913,SLR_Covidence_Data_Extraction__66_files[[#This Row],[Study ID_1]],'Coded Segments'!$D$2:$D$913,SLR_Covidence_Data_Extraction__66_files[[#Headers],[Ethical Concerns (EC) > EC_Environmental sustainability]]) -> 0 | AR11: =+COUNTIFS('Coded Segments'!$C$2:$C$913,SLR_Covidence_Data_Extraction__66_files[[#This Row],[Study ID_1]],'Coded Segments'!$D$2:$D$913,SLR_Covidence_Data_Extraction__66_files[[#Headers],[Ethical Concerns (EC) > EC_Payment]]) -> 0 | AS11: =+COUNTIFS('Coded Segments'!$C$2:$C$912,SLR_Covidence_Data_Extraction__66_files[[#This Row],[Study ID_1]],'Coded Segments'!$D$2:$D$912,SLR_Covidence_Data_Extraction__66_files[[#Headers],[Ethical Concerns (EC) > EC_Quality]]) -> 0 | AT11: =+COUNTIFS('Coded Segments'!$C$2:$C$913,SLR_Covidence_Data_Extraction__66_files[[#This Row],[Study ID_1]],'Coded Segments'!$D$2:$D$913,SLR_Covidence_Data_Extraction__66_files[[#Headers],[Ethical Concerns (EC) > EC_Translators’ role & status]]) -> 0 | AU11: =+COUNTIFS('Coded Segments'!$C$2:$C$913,SLR_Covidence_Data_Extraction__66_files[[#This Row],[Study ID_1]],'Coded Segments'!$D$2:$D$913,SLR_Covidence_Data_Extraction__66_files[[#Headers],[Ethical Concerns (EC) > EC_Other]]) -> 0 | AV11: =+COUNTIFS('Coded Segments'!$C$2:$C$913,SLR_Covidence_Data_Extraction__66_files[[#This Row],[Study ID_1]],'Coded Segments'!$D$2:$D$913,SLR_Covidence_Data_Extraction__66_files[[#Headers],[Literacy (LIT) > LIT_Generic]]) -> 1 | AW11: =+COUNTIFS('Coded Segments'!$C$2:$C$913,SLR_Covidence_Data_Extraction__66_files[[#This Row],[Study ID_1]],'Coded Segments'!$D$2:$D$913,SLR_Covidence_Data_Extraction__66_files[[#Headers],[Literacy (LIT) > LIT_None ]]) -> 0 | AX11: =+COUNTIFS('Coded Segments'!$C$2:$C$913,SLR_Covidence_Data_Extraction__66_files[[#This Row],[Study ID_1]],'Coded Segments'!$D$2:$D$913,SLR_Covidence_Data_Extraction__66_files[[#Headers],[Literacy (LIT) > LIT_Low ]]) -> 0 | AY11: =+COUNTIFS('Coded Segments'!$C$2:$C$913,SLR_Covidence_Data_Extraction__66_files[[#This Row],[Study ID_1]],'Coded Segments'!$D$2:$D$913,SLR_Covidence_Data_Extraction__66_files[[#Headers],[Literacy (LIT) > LIT_High]]) -> 0
A12: 61 | B12: LMSAI6DE | C12: Slessor 2020 | D12: Tenacious technophobes or nascent technophiles? A survey of the technological practices and needs of literary translators | E12: Stephen Slessor E-mail: stephen.slessor@gmail.com ORCID: 0000-0002-9206-5674 | F12: School of Translation and Interpretation, University of Ottawa, Ottawa, Canada | G12: Canada | H12: 2019/07/29 | I12: =LEFT(SLR_Covidence_Data_Extraction__66_files[[#This Row],[Publication date]],4) -> 2019 | J12: Canada | K12: To interrogate and challenge the common assumption that literary translation is a unique, non-repetitive practice for which digital tools have few practical applications | L12: Questionnaire | P12: - | Q12: - | R12: 15 | U12: Professional associations networks | V12: Online | X12: This work was supported by the Social Sciences and Humanities Research Council of Canada. | Y12: Literary translators members of the Literary Translators’ Association of Canada (LTAC) | Z12: Professional translators | AA12: Literary | AB12: 40 | AC12: 40 | AD12: 1. High Adoption of Standard Digital Tools The sources indicate that literary translators have largely integrated standard computer tools into their workflows. • Text Processing: Almost all respondents (98%) use standard word processors to compose their translations. While many still receive paper copies of source texts (67%), 80% receive them via email, facilitating the use of digital research methods. • Research Resources: Use of electronic resources for linguistic and cultural research is nearly universal. General electronic dictionaries and general search engines are both used by 93.2% of participants. • Secondary Resources: There is significant reliance on translation search engines like Linguee (75%), multi-domain term banks (70.5%), and online forums for translators (70.5%). 2. Ad Hoc Terminology Management While literary translators frequently engage in terminology work, they rarely use professional software for it. • Creation of Lists: Just over half (52%) of respondents create word lists or terminology databases. • Format Preference: Most prefer flexible but manual formats; 74% keep these lists in word processing files and 26% use spreadsheets. Only 13% reported using specialised terminology files. 3. Low Use of Specialised CAT and MT Tools A major finding is that specialized translation technologies, common in technical fields, have very low adoption rates in the literary domain. • Translation Memory (TM): A strong majority (77.5%) reported never using TM for literary work. • Machine Translation (MT): Use of MT is similarly low, with 70% stating they never use it. • Concordancers: Despite the potential for stylistic research, 87.5% never use monolingual or bilingual concordancers. 4. Barriers to Technology Adoption The sources identify several reasons why literary translators avoid specialised tools: • Suitability: The most common reason for rejection is the belief that these tools are not suitable for literary work, often due to the perceived lack of repetition in the genre. • Cost: The high price of specialized platforms (sometimes exceeding $1,000 per year) is a significant deterrent for a profession that is generally not high-earning. • Lack of Familiarity: Over 40% of those who do not use CAT tools reported that they either did not know what the tools were or did not know how to use them. 5. Creative and "Off-Label" Uses Interestingly, the small minority of translators who do use specialised technology often apply it in "creative" ways that differ from standard industry practice. • TM for Formatting: Some use TM software to maintain complex formatting or to create searchable "bitext" back-ups rather than for leveraging repetitive segments. • MT for Brainstorming: Users of MT often use it as a research aid to find synonyms or verify proper nouns rather than as a primary translation tool. • Voice Recognition: One respondent used dictation software specifically to simulate the feeling of "generating ideas on the spot" like a radio host. 6. Future Needs and "Wish List" When asked to design an ideal tool, participants expressed needs that align with current technological trends, even if they were unaware of them. Their requirements included tools for capturing printed text via camera, automated glossary creation, and searchable databases of all published books to track down quotations. The researcher concludes that while translators may seem resistant to technology, they actually have a broad range of ad hoc needs that current digital resources do not yet fully meet. | AE12: 1. Integration of Standard over Specialised Tools The researcher established a baseline for Canadian literary translators, concluding that they make extensive use of standard computer tools (such as word processors) and electronic resources (such as online dictionaries and search engines) to support their work. However, there is little use of more specialised technologies like Translation Memory (TM) or Machine Translation (MT), which are often perceived as unsuitable for the stylistic complexities of literary texts. 2. Barriers to Specialised Technology Adoption The study concludes that several significant barriers prevent the adoption of Computer-Assisted Translation (CAT) tools in the literary domain. Beyond the perceived unsuitability for non-repetitive texts, the high cost of professional platforms and a general lack of familiarity with the software act as major deterrents. 3. The "Creative" and "Ad Hoc" Use of Technology A significant conclusion is that a small minority of literary translators employ specialised tools in unexpected or "creative" ways that differ from standard industry practices. For instance, some use TM for maintaining complex formatting rather than for repetitive segments, or use MT as a research aid for synonyms rather than for generating primary output. The researcher concludes that translators have a broad range of ad hoc needs—particularly for linguistic and cultural research—that are not currently met by existing specialised tools. 4. Limitations of Current Training Models The survey revealed no apparent relationship between having received technology training and the actual use of specialised translation tools. This led the author to conclude that current training models may need to be rethought for literary translators, focusing more on awareness-raising, sharing best practices, and highlighting the "affordances" (potential uses) of various tools. 5. Future Recommendations for the Industry Ultimately, the study recommends that future developments and research should focus on improving digital tools to specifically support the research-heavy, non-repetitive nature of literary work. The author concludes that for stabilisation to occur, literary translators must be actively included in the dialogue between researchers and developers to ensure that future technology is both accessible and relevant to their unique workflow. | AF12: • Standard tools and electronic resources: Refers to the technologies (such as word processors and online dictionaries) that literary translators use extensively in their daily practice. • Specialised technologies / CAT tools: The term for advanced translation software (like Translation Memory) that currently sees little use in the literary domain but is noted for having potential "suitable applications". • Uptake of technology: Used to describe the expected increasing adoption of digital tools as the profession evolves. • Affordances of tools: A central concept in the conclusion, referring to the potential uses or creative applications of a tool that might not be immediately obvious to the user. • Ad hoc needs: Describes the specific, research-heavy requirements of literary translators—particularly for linguistic and cultural research—that existing specialised tools often fail to meet. • Concordancers and corpus-based research: Highlighted as specific areas where translators showed interest, provided the functionality of tools and availability of suitable corpora are improved. • Ongoing dialogue: The recommended process of collaboration between researchers, developers, and translators to ensure future tools are relevant to literary work. • Active professional literary translators: The key stakeholder group that the author concludes must be granted a greater role in the broader discussion on technology. • Computer age: The current era that the author suggests literary translators can finally "make their peace with" if their unique needs are addressed through inclusive innovation. • Best practices: The conclusion suggests that sharing these practices, rather than traditional training models, may be more effective for this specific group of professionals. | AG12: Linguistic challenges; Technical aspects | AH12: =+COUNTIFS('Coded Segments'!$C$2:$C$913,SLR_Covidence_Data_Extraction__66_files[[#This Row],[Study ID_1]],'Coded Segments'!$D$2:$D$913,SLR_Covidence_Data_Extraction__66_files[[#Headers],[Adoption (AD) > AD_High]]) -> 0 | AI12: =+COUNTIFS('Coded Segments'!$C$2:$C$913,SLR_Covidence_Data_Extraction__66_files[[#This Row],[Study ID_1]],'Coded Segments'!$D$2:$D$913,SLR_Covidence_Data_Extraction__66_files[[#Headers],[Adoption (AD) > AD_Moderate]]) -> 1 | AJ12: =+COUNTIFS('Coded Segments'!$C$2:$C$913,SLR_Covidence_Data_Extraction__66_files[[#This Row],[Study ID_1]],'Coded Segments'!$D$2:$D$913,SLR_Covidence_Data_Extraction__66_files[[#Headers],[Adoption (AD) > AD_Low]]) -> 1 | AK12: =+COUNTIFS('Coded Segments'!$C$2:$C$913,SLR_Covidence_Data_Extraction__66_files[[#This Row],[Study ID_1]],'Coded Segments'!$D$2:$D$913,SLR_Covidence_Data_Extraction__66_files[[#Headers],[Adoption (AD) > AD_None]]) -> 0 | AL12: =+COUNTIFS('Coded Segments'!$C$2:$C$913,SLR_Covidence_Data_Extraction__66_files[[#This Row],[Study ID_1]],'Coded Segments'!$D$2:$D$913,SLR_Covidence_Data_Extraction__66_files[[#Headers],[Attitude (ATT) > ATT_Negative]]) -> 3 | AM12: =+COUNTIFS('Coded Segments'!$C$2:$C$913,SLR_Covidence_Data_Extraction__66_files[[#This Row],[Study ID_1]],'Coded Segments'!$D$2:$D$913,SLR_Covidence_Data_Extraction__66_files[[#Headers],[Attitude (ATT) > ATT_Positive]]) -> 0 | AN12: =+COUNTIFS('Coded Segments'!$C$2:$C$913,SLR_Covidence_Data_Extraction__66_files[[#This Row],[Study ID_1]],'Coded Segments'!$D$2:$D$913,SLR_Covidence_Data_Extraction__66_files[[#Headers],[Ethical Concerns (EC) > EC_Bias]]) -> 0 | AO12: =+COUNTIFS('Coded Segments'!$C$2:$C$913,SLR_Covidence_Data_Extraction__66_files[[#This Row],[Study ID_1]],'Coded Segments'!$D$2:$D$913,SLR_Covidence_Data_Extraction__66_files[[#Headers],[Ethical Concerns (EC) > EC_Copyright]]) -> 0 | AP12: =+COUNTIFS('Coded Segments'!$C$2:$C$913,SLR_Covidence_Data_Extraction__66_files[[#This Row],[Study ID_1]],'Coded Segments'!$D$2:$D$913,SLR_Covidence_Data_Extraction__66_files[[#Headers],[Ethical Concerns (EC) > EC_Data safety & confidentiality]]) -> 0 | AQ12: =+COUNTIFS('Coded Segments'!$C$2:$C$913,SLR_Covidence_Data_Extraction__66_files[[#This Row],[Study ID_1]],'Coded Segments'!$D$2:$D$913,SLR_Covidence_Data_Extraction__66_files[[#Headers],[Ethical Concerns (EC) > EC_Environmental sustainability]]) -> 0 | AR12: =+COUNTIFS('Coded Segments'!$C$2:$C$913,SLR_Covidence_Data_Extraction__66_files[[#This Row],[Study ID_1]],'Coded Segments'!$D$2:$D$913,SLR_Covidence_Data_Extraction__66_files[[#Headers],[Ethical Concerns (EC) > EC_Payment]]) -> 1 | AS12: =+COUNTIFS('Coded Segments'!$C$2:$C$912,SLR_Covidence_Data_Extraction__66_files[[#This Row],[Study ID_1]],'Coded Segments'!$D$2:$D$912,SLR_Covidence_Data_Extraction__66_files[[#Headers],[Ethical Concerns (EC) > EC_Quality]]) -> 2 | AT12: =+COUNTIFS('Coded Segments'!$C$2:$C$913,SLR_Covidence_Data_Extraction__66_files[[#This Row],[Study ID_1]],'Coded Segments'!$D$2:$D$913,SLR_Covidence_Data_Extraction__66_files[[#Headers],[Ethical Concerns (EC) > EC_Translators’ role & status]]) -> 0 | AU12: =+COUNTIFS('Coded Segments'!$C$2:$C$913,SLR_Covidence_Data_Extraction__66_files[[#This Row],[Study ID_1]],'Coded Segments'!$D$2:$D$913,SLR_Covidence_Data_Extraction__66_files[[#Headers],[Ethical Concerns (EC) > EC_Other]]) -> 0 | AV12: =+COUNTIFS('Coded Segments'!$C$2:$C$913,SLR_Covidence_Data_Extraction__66_files[[#This Row],[Study ID_1]],'Coded Segments'!$D$2:$D$913,SLR_Covidence_Data_Extraction__66_files[[#Headers],[Literacy (LIT) > LIT_Generic]]) -> 1 | AW12: =+COUNTIFS('Coded Segments'!$C$2:$C$913,SLR_Covidence_Data_Extraction__66_files[[#This Row],[Study ID_1]],'Coded Segments'!$D$2:$D$913,SLR_Covidence_Data_Extraction__66_files[[#Headers],[Literacy (LIT) > LIT_None ]]) -> 1 | AX12: =+COUNTIFS('Coded Segments'!$C$2:$C$913,SLR_Covidence_Data_Extraction__66_files[[#This Row],[Study ID_1]],'Coded Segments'!$D$2:$D$913,SLR_Covidence_Data_Extraction__66_files[[#Headers],[Literacy (LIT) > LIT_Low ]]) -> 0 | AY12: =+COUNTIFS('Coded Segments'!$C$2:$C$913,SLR_Covidence_Data_Extraction__66_files[[#This Row],[Study ID_1]],'Coded Segments'!$D$2:$D$913,SLR_Covidence_Data_Extraction__66_files[[#Headers],[Literacy (LIT) > LIT_High]]) -> 0
A13: 42 | B13: M53E6RX8 | C13: Rossi 2019 | D13: Uses and perceptions of Machine Translation at the European Commission | E13: Caroline Rossi E-mail: caroline.rossi@univ-grenoble-alpes.fr | F13: Lecturer involved in translator training at Université Grenoble Alpe | G13: France | H13: 2019/01 | I13: =LEFT(SLR_Covidence_Data_Extraction__66_files[[#This Row],[Publication date]],4) -> 2019 | J13: Europe | K13: To understand the current uses and perceptions of machine translation (MT) and post-editing (PE) within the Directorate-General for Translation (DGT) of the European Commission. | L13: Questionnaire | N13: Interviews | P13: - | Q13: - | R13: =28+6 -> 34 | S13: 2017 | T13: 2017 | U13: Other: European Commission's DGT | V13: Online | W13: Offline | Y13: DGT translators | Z13: Professional translators | AA13: Legal | AB13: =89+10 -> 99 | AC13: 89 (survey) + 10 (interviews) | AD13: 1. High Acceptance but Polarised Perception • Widespread Use: Overall MT acceptance was found to be high, with 89% of respondents using the tool either "systematically" (43%) or "in some cases" (46%). • The "Threat" Narrative: Despite high use, perceptions were polarised; 40% of translators in the ethnographic phase viewed MT as a "threat" to the human translator, while others viewed it as a "typing aid" or a "constant progress". 2. Predictors of Use: Fear vs. Utility The researchers used multiple linear regressions to determine what actually predicts whether a translator will use the tool: • The Weight of Fear: Two factors introduced by the researchers—"fear of MT" (security) and "perceived impact"—had a more significant impact on actual use than traditional measures like "perceived usefulness" or "ease of use". • Social Image: Perceived usefulness was significantly influenced by "image" (whether using the tool enhances one's professional standing) and "subjective norm" (the influence of peers), rather than just the tool's performance. 3. The Quality Paradox A major result was that MT output quality was virtually unrelated to whether translators found the tool useful. This suggests that even if the machine provides relatively good output, other factors—such as cognitive load or the feeling of being "trapped" by the segments—can hinder the translator's activity. 4. The Correlation Between Knowledge and Fear The study identified a direct link between technical literacy and anxiety: • Knowledge Gap: There was a significant correlation between fear and a lack of knowledge about how MT works. • The Empowerment Factor: Translators who perceived MT as a threat were consistently those who had the lowest scores for MT knowledge. While half the sample understood how the system worked, the researchers concluded this was not enough to truly "empower" the staff. 5. Interpretive Flexibility (Beyond Speed) The study found that translators use MT for a wide variety of creative purposes beyond just saving time: • Usage Profiles: While 37.9% use MT primarily to save time, others use it for meaning (16.8%), terminology (10.5%), and inspiration (4.2%). • Expert Agency: Approximately 25% of translators provided negative feedback regarding "usable" output, demonstrating "interpretive flexibility" by knowing exactly when to discard MT if it lacked appropriate structure or did not make sense. 6. Language and Departmental Disparities • High-Use Departments: Translators in the Spanish (ES), Italian (IT), Portuguese (PT), and Romanian (RO) departments showed the highest adoption rates. • Low-Use Departments: The English (EN) department had the lowest scores for actual use, with only one out of 16 surveyed translators using MT systematically. The French (FR) department also fell into the low-use group in this specific data set. | AE13: 1. Perceptions Outweigh Performance The researchers conclude that while technology acceptance is high among DGT staff, actual use is driven by internal feelings rather than the machine's accuracy. Their analysis showed that perceptions of MT (such as image and fear) have a strong impact on both perceived usefulness and actual use, whereas traditional factors like MT output quality were found to be virtually unrelated to how useful a translator found the tool. 2. Tasks vs. Activity: The Failure of Standard Models A central conclusion is the need to distinguish between translation tasks (the automated steps in a workflow) and translator activity (the complex cognitive and ergonomic process). • The study concludes that Technology Acceptance Models (TAMs) often fail because they focus on tasks rather than the "human-computer interactions" (HCIs) that involve cognitive load, feelings, and diverse experiences. • While the DGT’s workflow is "extremely well-designed" for management, it does not necessarily ease the psychological or cognitive demands placed on the individual translator. 3. "Interpretive Flexibility" and Professional Trust The authors conclude that institutional translators exhibit "interpretive flexibility," using MT creatively for inspiration or terminology rather than just speed. • The results show that translators know very well when and why to discard machine output if it lacks sense or structure. • Consequently, the researchers conclude that translators’ expertise can and should be trusted; the decision of when it is appropriate to use MT should remain with the human professional rather than being dictated by rigid guidelines. 4. The Knowledge-Empowerment Gap The study identifies a critical link between technical knowledge and professional anxiety. • The researchers conclude that "fear of MT" is significantly correlated with a lack of understanding of how the system works. • However, they also conclude that simply knowing the technical facts is "obviously not enough" to truly empower staff. True empowerment requires giving translators more control over their environments and involving them as active "actors" in technology development rather than just passive users. 5. Training for Critical Thinking Finally, the study concludes that these institutional insights offer new perspectives for translator training. • Rather than just teaching post-editing skills, trainers should encourage students to think critically about their own cognitive processes when interacting with machines. • By allowing students to choose when to use MT and justify those choices, they are better prepared for the "interpretive flexibility" required in the professional field. | AF13: • Current uses and perceptions: The central focus of the study, highlighting that the research sought to understand both what translators do and how they feel. • Machine translation (MT) and post-editing (PE): The specific technological artifacts and professional tasks that were the subject of the institutional mapping. • Ethnographic methods and survey analysis: The two primary research approaches used to gather the data required to account for technology acceptance. • Technology acceptance: The primary professional metric the study aimed to measure and predict using adapted models. • Perceptions of MT: A term used to describe the subjective factors (such as image and fear) that the authors conclude have a "strong impact" on whether a tool is used. • Perceived usefulness and actual use: Two specific variables that the authors conclude are heavily influenced by subjective feelings rather than just technical output quality. • HCIs (Human-computer interactions): A broad term used by the authors to designate the complex and diverse relationship between the translator and the machine. • Experiences and feelings: The psychological and ergonomic factors that the authors conclude existing models "partly fail to capture". • Translator trainers: The professional role assumed by the authors in the conclusion, reflecting their desire to apply these results to educational curricula. • Translators’ roles: The evolving identity of the human professional, which the authors hope to characterize in "diverse ways" to open up new professional perspectives. | AG13: Technical aspects; Training needs; Ethical aspects | AH13: =+COUNTIFS('Coded Segments'!$C$2:$C$913,SLR_Covidence_Data_Extraction__66_files[[#This Row],[Study ID_1]],'Coded Segments'!$D$2:$D$913,SLR_Covidence_Data_Extraction__66_files[[#Headers],[Adoption (AD) > AD_High]]) -> 1 | AI13: =+COUNTIFS('Coded Segments'!$C$2:$C$913,SLR_Covidence_Data_Extraction__66_files[[#This Row],[Study ID_1]],'Coded Segments'!$D$2:$D$913,SLR_Covidence_Data_Extraction__66_files[[#Headers],[Adoption (AD) > AD_Moderate]]) -> 0 | AJ13: =+COUNTIFS('Coded Segments'!$C$2:$C$913,SLR_Covidence_Data_Extraction__66_files[[#This Row],[Study ID_1]],'Coded Segments'!$D$2:$D$913,SLR_Covidence_Data_Extraction__66_files[[#Headers],[Adoption (AD) > AD_Low]]) -> 0 | AK13: =+COUNTIFS('Coded Segments'!$C$2:$C$913,SLR_Covidence_Data_Extraction__66_files[[#This Row],[Study ID_1]],'Coded Segments'!$D$2:$D$913,SLR_Covidence_Data_Extraction__66_files[[#Headers],[Adoption (AD) > AD_None]]) -> 0 | AL13: =+COUNTIFS('Coded Segments'!$C$2:$C$913,SLR_Covidence_Data_Extraction__66_files[[#This Row],[Study ID_1]],'Coded Segments'!$D$2:$D$913,SLR_Covidence_Data_Extraction__66_files[[#Headers],[Attitude (ATT) > ATT_Negative]]) -> 3 | AM13: =+COUNTIFS('Coded Segments'!$C$2:$C$913,SLR_Covidence_Data_Extraction__66_files[[#This Row],[Study ID_1]],'Coded Segments'!$D$2:$D$913,SLR_Covidence_Data_Extraction__66_files[[#Headers],[Attitude (ATT) > ATT_Positive]]) -> 2 | AN13: =+COUNTIFS('Coded Segments'!$C$2:$C$913,SLR_Covidence_Data_Extraction__66_files[[#This Row],[Study ID_1]],'Coded Segments'!$D$2:$D$913,SLR_Covidence_Data_Extraction__66_files[[#Headers],[Ethical Concerns (EC) > EC_Bias]]) -> 0 | AO13: =+COUNTIFS('Coded Segments'!$C$2:$C$913,SLR_Covidence_Data_Extraction__66_files[[#This Row],[Study ID_1]],'Coded Segments'!$D$2:$D$913,SLR_Covidence_Data_Extraction__66_files[[#Headers],[Ethical Concerns (EC) > EC_Copyright]]) -> 0 | AP13: =+COUNTIFS('Coded Segments'!$C$2:$C$913,SLR_Covidence_Data_Extraction__66_files[[#This Row],[Study ID_1]],'Coded Segments'!$D$2:$D$913,SLR_Covidence_Data_Extraction__66_files[[#Headers],[Ethical Concerns (EC) > EC_Data safety & confidentiality]]) -> 1 | AQ13: =+COUNTIFS('Coded Segments'!$C$2:$C$913,SLR_Covidence_Data_Extraction__66_files[[#This Row],[Study ID_1]],'Coded Segments'!$D$2:$D$913,SLR_Covidence_Data_Extraction__66_files[[#Headers],[Ethical Concerns (EC) > EC_Environmental sustainability]]) -> 0 | AR13: =+COUNTIFS('Coded Segments'!$C$2:$C$913,SLR_Covidence_Data_Extraction__66_files[[#This Row],[Study ID_1]],'Coded Segments'!$D$2:$D$913,SLR_Covidence_Data_Extraction__66_files[[#Headers],[Ethical Concerns (EC) > EC_Payment]]) -> 0 | AS13: =+COUNTIFS('Coded Segments'!$C$2:$C$912,SLR_Covidence_Data_Extraction__66_files[[#This Row],[Study ID_1]],'Coded Segments'!$D$2:$D$912,SLR_Covidence_Data_Extraction__66_files[[#Headers],[Ethical Concerns (EC) > EC_Quality]]) -> 0 | AT13: =+COUNTIFS('Coded Segments'!$C$2:$C$913,SLR_Covidence_Data_Extraction__66_files[[#This Row],[Study ID_1]],'Coded Segments'!$D$2:$D$913,SLR_Covidence_Data_Extraction__66_files[[#Headers],[Ethical Concerns (EC) > EC_Translators’ role & status]]) -> 3 | AU13: =+COUNTIFS('Coded Segments'!$C$2:$C$913,SLR_Covidence_Data_Extraction__66_files[[#This Row],[Study ID_1]],'Coded Segments'!$D$2:$D$913,SLR_Covidence_Data_Extraction__66_files[[#Headers],[Ethical Concerns (EC) > EC_Other]]) -> 0 | AV13: =+COUNTIFS('Coded Segments'!$C$2:$C$913,SLR_Covidence_Data_Extraction__66_files[[#This Row],[Study ID_1]],'Coded Segments'!$D$2:$D$913,SLR_Covidence_Data_Extraction__66_files[[#Headers],[Literacy (LIT) > LIT_Generic]]) -> 0 | AW13: =+COUNTIFS('Coded Segments'!$C$2:$C$913,SLR_Covidence_Data_Extraction__66_files[[#This Row],[Study ID_1]],'Coded Segments'!$D$2:$D$913,SLR_Covidence_Data_Extraction__66_files[[#Headers],[Literacy (LIT) > LIT_None ]]) -> 0 | AX13: =+COUNTIFS('Coded Segments'!$C$2:$C$913,SLR_Covidence_Data_Extraction__66_files[[#This Row],[Study ID_1]],'Coded Segments'!$D$2:$D$913,SLR_Covidence_Data_Extraction__66_files[[#Headers],[Literacy (LIT) > LIT_Low ]]) -> 2 | AY13: =+COUNTIFS('Coded Segments'!$C$2:$C$913,SLR_Covidence_Data_Extraction__66_files[[#This Row],[Study ID_1]],'Coded Segments'!$D$2:$D$913,SLR_Covidence_Data_Extraction__66_files[[#Headers],[Literacy (LIT) > LIT_High]]) -> 1
A14: 40 | B14: PYXMRFVD | C14: NunesVieira 2020 | D14: Translating perceptions and managing expectations: an analysis of management and production perspectives on machine translation | E14: Lucas Nunes Vieira E-mail: l.nunesvieira@bristol.ac.uk | F14: School of Modern Languages, University of Bristol, UK | G14: UK | H14: 2019/08/14 | I14: =LEFT(SLR_Covidence_Data_Extraction__66_files[[#This Row],[Publication date]],4) -> 2019 | J14: Worldwide | K14: To conduct a contrastive analysis of stakeholder perspectives - specifically those in management and production - regarding the use of machine translation (MT) in the professional translation industry. | N14: Interviews | S14: 2016 | T14: 2017 | U14: Personal contacts; Social media; Professional associations networks; Other: Attendees of a linguistics congress in Spain | V14: Online | X14: This work was supported by Spanish Ministry of Science, Innovation and Universities: [grant number REF CAS17/00385]. The study was partly funded by a José Castillejo mobility grant held by Dr Elisa Alonso (one of the authors) during a research stay at the University of Bristol in 2018 (REF CAS17/00385). | Y14: Project managers, freelance and in-house translators | Z14: Project managers | AA14: General | AB14: 29 | AC14: 29 | AD14: 1. Stakeholder Dissonance and Sentiment The researchers used sentiment coding to contrast the views of Management (project managers/owners) and Production (translators). • Management’s Balanced View: Managers held a relatively balanced stance, with similar numbers of positive and negative comments. They viewed MT pragmatically as a tool to navigate the "iron triangle" of speed, cost, and quality. • Production’s Negative View: Translators were disproportionately negative, specifically regarding target-text quality, tools/interfaces, and productivity. • The Communication Gap: A major result was the discrepancy in "Flow of Information." Translators often felt "alienated" or "detached" from the wider project strategy, receiving minimal instructions, while managers had a "panoramic view" but lacked direct experience with the cognitive effort of post-editing. 2. Quality, Agency, and Professional Identity The study revealed a fundamental conflict regarding what constitutes a "successful" translation. • The "Good Enough" Conflict: Managers were more willing to accept "fit-for-purpose" or "good enough" quality to meet client budgets or deadlines. Translators, however, reported an inherent "sense of duty" to the text and felt "annoyed" or "uncomfortable" delivering anything below high human standards. • Responsibility for Error: Translators expressed anxiety over agency, feeling that while the machine generated the text, they remained the "experts" who would be blamed for any undetected errors. • Quality Oversight: Managers reported very few quality complaints from clients, leading them to believe MT implementation was successful—a view that ran counter to the translators’ internal dissatisfaction with the final product. 3. Economic and Pricing Friction The uncertainty of MT quality created significant challenges for quoting and compensation. • The Productivity Paradox: Pricing was often based on estimated speed gains. However, when MT quality was lower than expected, translators suffered a loss in earning power because the task took longer than the managers' "over-expectations" predicted. • Negotiation Conflicts: Managers reported "slight conflicts" when projects took four hours instead of two, noting that because clients were often on "squeezed" budgets, it was not always possible to renegotiate the fee. 4. Technology Awareness and Interfaces • The Neural Gap: At the time of the interviews (2016–2017), Neural MT (NMT) was mentioned exclusively by managers. This suggested that managers were more attuned to the evolving technological landscape, while translators were primarily focused on the immediate task at hand. • Polarizing Tools: Client-developed, cloud-based tools were a source of major dissatisfaction for translators if they lacked the features of familiar professional interfaces, though some found them useful if the MT quality was exceptionally high. | AE14: 1. MT as a Source of Market Uncertainty The researchers conclude that MT adds complexity to the "iron triangle" of speed, cost, and quality. • Because MT quality is inherently unpredictable, it is difficult for managers to provide precise quotes or for translators to estimate their effort beforehand. • This uncertainty often leads to mismatched expectations, where clients and managers may have over-expectations of productivity that do not align with the reality of the translator's work. 2. Local Attachment vs. Global Detachment A central conclusion is the identified gap between the "local" focus of the translator and the "global" focus of the manager. • Translators exhibit a "local attachment" to the text, driven by a professional "sense of duty" to maintain high standards, even when a client asks for "good enough" quality. • Managers maintain a "global detachment" or "panoramic view," allowing them to make pragmatic, business-oriented decisions about quality compromises that translators often find "annoying" or "uncomfortable". 3. Professional Alienation and Fragmentation The study concludes that the current structure of the language industry alienates translators from business strategy. • Translators are frequently relegated to the position of "peripheral contributors" or "technology users" rather than strategic partners. • This fragmentation means that translators—who are the "core" of the business—often lack the contextual oversight and information flow needed to negotiate fair pay and realistic deadlines. 4. Reframing the "Threat" of MT The authors conclude that framing MT as a "threat" to jobs is a "misguided" perspective that masks deeper structural problems. • The real issue is not the technology itself, but the societal and business dynamics surrounding its use, such as unrealistic perceptions of its capabilities and the resulting downward pressure on word rates. 5. The Need for "Translatorial Agency" in Business Finally, the study concludes with two primary recommendations for the industry and academia: • Increased Involvement: Translators must be more involved in the management, estimation, and client-communication phases of projects to bridge the gap between production reality and managerial expectation. • Radical Training Reform: As noted in our conversation history, the researchers argue that translator training should move beyond just "instrumental" skills like post-editing and instead foster a "conceptual understanding" of business dynamics, empowering translators to shape the market they are adapting to. | AF14: • Uncertainty: The defining characteristic that MT adds to translation services, making it difficult to provide precise quotes or predict the effort required for a task. • Work fragmentation: Refers to how the complex service provision networks of the modern industry break projects into isolated steps, often separating the person doing the translation from the person managing the client. • Field of influence: Used to describe the restricted position of the translator, whose agency is often limited to the textual core of a project while they remain excluded from broader decision-making. • Alienating / Alienation: The process by which translators are detached from business strategy, relegated to being "technology users" rather than strategic partners. • Estimation and client-communication: The two specific areas where the authors argue translators must become more involved to bridge the gap between production reality and managerial expectations. • Integrated roles: The study’s primary recommendation for the future, suggesting that translators should play a broader role within translation supply chains. • Threat: A term the authors argue should be reframed; they conclude that the "threat" to the profession is not the technology itself, but rather the unrealistic perceptions and mismatched expectations surrounding its use. | AG14: Technical aspects; Working conditions; Ethical aspects | AH14: =+COUNTIFS('Coded Segments'!$C$2:$C$913,SLR_Covidence_Data_Extraction__66_files[[#This Row],[Study ID_1]],'Coded Segments'!$D$2:$D$913,SLR_Covidence_Data_Extraction__66_files[[#Headers],[Adoption (AD) > AD_High]]) -> 0 | AI14: =+COUNTIFS('Coded Segments'!$C$2:$C$913,SLR_Covidence_Data_Extraction__66_files[[#This Row],[Study ID_1]],'Coded Segments'!$D$2:$D$913,SLR_Covidence_Data_Extraction__66_files[[#Headers],[Adoption (AD) > AD_Moderate]]) -> 0 | AJ14: =+COUNTIFS('Coded Segments'!$C$2:$C$913,SLR_Covidence_Data_Extraction__66_files[[#This Row],[Study ID_1]],'Coded Segments'!$D$2:$D$913,SLR_Covidence_Data_Extraction__66_files[[#Headers],[Adoption (AD) > AD_Low]]) -> 0 | AK14: =+COUNTIFS('Coded Segments'!$C$2:$C$913,SLR_Covidence_Data_Extraction__66_files[[#This Row],[Study ID_1]],'Coded Segments'!$D$2:$D$913,SLR_Covidence_Data_Extraction__66_files[[#Headers],[Adoption (AD) > AD_None]]) -> 0 | AL14: =+COUNTIFS('Coded Segments'!$C$2:$C$913,SLR_Covidence_Data_Extraction__66_files[[#This Row],[Study ID_1]],'Coded Segments'!$D$2:$D$913,SLR_Covidence_Data_Extraction__66_files[[#Headers],[Attitude (ATT) > ATT_Negative]]) -> 5 | AM14: =+COUNTIFS('Coded Segments'!$C$2:$C$913,SLR_Covidence_Data_Extraction__66_files[[#This Row],[Study ID_1]],'Coded Segments'!$D$2:$D$913,SLR_Covidence_Data_Extraction__66_files[[#Headers],[Attitude (ATT) > ATT_Positive]]) -> 1 | AN14: =+COUNTIFS('Coded Segments'!$C$2:$C$913,SLR_Covidence_Data_Extraction__66_files[[#This Row],[Study ID_1]],'Coded Segments'!$D$2:$D$913,SLR_Covidence_Data_Extraction__66_files[[#Headers],[Ethical Concerns (EC) > EC_Bias]]) -> 0 | AO14: =+COUNTIFS('Coded Segments'!$C$2:$C$913,SLR_Covidence_Data_Extraction__66_files[[#This Row],[Study ID_1]],'Coded Segments'!$D$2:$D$913,SLR_Covidence_Data_Extraction__66_files[[#Headers],[Ethical Concerns (EC) > EC_Copyright]]) -> 0 | AP14: =+COUNTIFS('Coded Segments'!$C$2:$C$913,SLR_Covidence_Data_Extraction__66_files[[#This Row],[Study ID_1]],'Coded Segments'!$D$2:$D$913,SLR_Covidence_Data_Extraction__66_files[[#Headers],[Ethical Concerns (EC) > EC_Data safety & confidentiality]]) -> 0 | AQ14: =+COUNTIFS('Coded Segments'!$C$2:$C$913,SLR_Covidence_Data_Extraction__66_files[[#This Row],[Study ID_1]],'Coded Segments'!$D$2:$D$913,SLR_Covidence_Data_Extraction__66_files[[#Headers],[Ethical Concerns (EC) > EC_Environmental sustainability]]) -> 0 | AR14: =+COUNTIFS('Coded Segments'!$C$2:$C$913,SLR_Covidence_Data_Extraction__66_files[[#This Row],[Study ID_1]],'Coded Segments'!$D$2:$D$913,SLR_Covidence_Data_Extraction__66_files[[#Headers],[Ethical Concerns (EC) > EC_Payment]]) -> 3 | AS14: =+COUNTIFS('Coded Segments'!$C$2:$C$912,SLR_Covidence_Data_Extraction__66_files[[#This Row],[Study ID_1]],'Coded Segments'!$D$2:$D$912,SLR_Covidence_Data_Extraction__66_files[[#Headers],[Ethical Concerns (EC) > EC_Quality]]) -> 4 | AT14: =+COUNTIFS('Coded Segments'!$C$2:$C$913,SLR_Covidence_Data_Extraction__66_files[[#This Row],[Study ID_1]],'Coded Segments'!$D$2:$D$913,SLR_Covidence_Data_Extraction__66_files[[#Headers],[Ethical Concerns (EC) > EC_Translators’ role & status]]) -> 3 | AU14: =+COUNTIFS('Coded Segments'!$C$2:$C$913,SLR_Covidence_Data_Extraction__66_files[[#This Row],[Study ID_1]],'Coded Segments'!$D$2:$D$913,SLR_Covidence_Data_Extraction__66_files[[#Headers],[Ethical Concerns (EC) > EC_Other]]) -> 0 | AV14: =+COUNTIFS('Coded Segments'!$C$2:$C$913,SLR_Covidence_Data_Extraction__66_files[[#This Row],[Study ID_1]],'Coded Segments'!$D$2:$D$913,SLR_Covidence_Data_Extraction__66_files[[#Headers],[Literacy (LIT) > LIT_Generic]]) -> 1 | AW14: =+COUNTIFS('Coded Segments'!$C$2:$C$913,SLR_Covidence_Data_Extraction__66_files[[#This Row],[Study ID_1]],'Coded Segments'!$D$2:$D$913,SLR_Covidence_Data_Extraction__66_files[[#Headers],[Literacy (LIT) > LIT_None ]]) -> 0 | AX14: =+COUNTIFS('Coded Segments'!$C$2:$C$913,SLR_Covidence_Data_Extraction__66_files[[#This Row],[Study ID_1]],'Coded Segments'!$D$2:$D$913,SLR_Covidence_Data_Extraction__66_files[[#Headers],[Literacy (LIT) > LIT_Low ]]) -> 0 | AY14: =+COUNTIFS('Coded Segments'!$C$2:$C$913,SLR_Covidence_Data_Extraction__66_files[[#This Row],[Study ID_1]],'Coded Segments'!$D$2:$D$913,SLR_Covidence_Data_Extraction__66_files[[#Headers],[Literacy (LIT) > LIT_High]]) -> 0
A15: 54 | B15: 64F8ERRS | C15: Macken 2020 | D15: Quantifying the Effect of Machine Translation in a High-Quality Human Translation Production Process | E15: Lieve Macken E-mail: Lieve.Macken@ugent.be | F15: Language and Translation Technology Team, Ghent University, Belgium | G15: Belgium | H15: 2020/04/23 | I15: =LEFT(SLR_Covidence_Data_Extraction__66_files[[#This Row],[Publication date]],4) -> 2020 | J15: Europe | K15: To assess the actual impact of machine translation (MT) on the translation workflow at the Directorate-General for Translation (DGT) of the European Commission. | L15: Questionnaire | O15: Other: Month-long, real-world study designed to measure the temporal and technical effort of professional translators when using machine translation (MT) compared to translating from scratch. | P15: - | Q15: - | R15: 6 | S15: 2018 | T15: 2018 | U15: Other: DGT | V15: Online | W15: Offline | Y15: Highly professional translators - each with at least 10 years of experience | Z15: Professional translators | AA15: General | AB15: 20 | AC15: 20 | AD15: 1. Productivity and Speed Gains The experiment quantified the "temporal effort" required for post-editing compared to translating from scratch: • Average Gains: On average, translators were 14% faster using Neural MT for Finnish (NMT-FI) and 12% faster using Statistical MT for French (SMT-FR). These gains are notably lower than those reported in previous similar studies. • The Individual Factor: Success was highly personal. In the Finnish department, all five analyzed translators saw speed gains (11%–21%). However, in the French department, two out of five translators were actually slower when using MT, with one suffering a 36% loss in productivity. • The "Incompressible" Verification Time: Even when the MT produced a "perfect" suggestion that required no editing, translators still spent an average of 2.05 to 3.22 seconds per word. This represents the time required for a professional to read, verify, and approve the output, which the researchers call "incompressible" time. 2. Technical Effort and Correlation Paradox The study measured "technical effort" using edit-distance metrics (HTER and CharacTER) to see if the amount of editing predicted the time spent: • Amount of Editing: Translators performed more editing on the Finnish NMT output than on the French SMT output. • Weak Correlations: Crucially, the study found only weak correlations between the number of edits and the total time spent post-editing. This suggests that technical effort (typing) is not a reliable proxy for temporal effort (the total work time), likely because cognitive effort (thinking and verifying) dominates the process. 3. User Perception and Psychological Impact The survey following the experiment provided insight into why professionals choose to use or avoid the tool: • Top Motivator: The reduction of typing effort was the most frequently cited reason for preferring MT. • Psychological Base: Translators highlighted the reassurance of "not having to start from scratch," describing the MT output as a "foundation" or "base" that makes the work feel partly done. • Deceptive Fluency: Finnish translators noted a specific risk with NMT: it produces fluent but inaccurate text that can "hide serious mistakes" which are only spotted upon deep inspection. • Use Cases: MT was perceived as most useful for long, repetitive, or "boring" texts, but less effective for creative translations, highly technical annexes, or documents where numbers and proper names might trigger "slightly crazy" suggestions. | AE15: 1. Measurable but Modest Productivity Gains The researchers concluded that MT provides measurable benefits in real-life translation scenarios, but these gains are significantly lower than those reported in earlier experimental or localisation-focused studies. • While previous literature cited by the authors reported throughput improvements of up to 74%, the actual gains at the DGT were only 12% for Statistical MT (French) and 14% for Neural MT (Finnish). • This suggests that in high-stakes institutional settings where texts are often legally binding, the "speed-up" effect of MT is restricted by the absolute necessity of human review. 2. The Superior Consistency of Neural MT A primary conclusion is that Neural Machine Translation (NMT) provides more consistently useful output than the older phrase-based Statistical MT (SMT). • All translators in the Finnish NMT group achieved speed gains. In contrast, the French SMT group saw significant individual variation, with some translators actually working up to 36% slower when attempting to use the machine suggestions. 3. The "Incompressible" Human Verification Time One of the study's most important findings is the identification of a "residual amount of time" that is incompressible regardless of the quality of the machine. • Even when provided with "perfect" machine output that required zero editing, translators still spent an average of 2.05 to 3.22 seconds per word just to read, verify, and approve the segment. • This proves that human cognitive verification is a fixed time-cost that automation cannot eliminate in a professional high-quality workflow. 4. Individual Variation and Productivity The study concludes that MT is not a "silver bullet" for productivity; it does not benefit every professional equally. • There were large variations in individual processing speeds, indicating that a translator's personal style and experience significantly influence whether MT acts as an aid or an impediment. 5. Failure of Technical Metrics as Proxies The researchers concluded that common industry metrics like HTER (edit distance) are not good indicators of temporal effort. • The study found only weak correlations between the amount of technical editing (typing) and the total time spent (thinking/verifying). This confirms that "number of edits" is a poor proxy for the actual cognitive effort involved in post-editing. 6. Psychological Alignment and Perception Finally, the study concludes that professional translators generally have a correct perception of their own speed gains. • The survey results showed that most translators correctly identified if the tool made them faster. • Beyond raw speed, the psychological benefit of having a "foundation" to build upon—avoiding the daunting nature of a "blank page"—is a major factor in the tool's acceptance. | AF15: • Machine translation: The primary technology being evaluated throughout the study. • Measurable benefits: Used to describe the average positive impact found when using MT in real-life translation scenarios. • Neural vs. statistical machine translation systems: The two technological paradigms compared, with neural translation systems noted for providing more consistently useful output. • Average speed gain: The specific metric (14% for Finnish and 12% for French) used to quantify productivity increases. • Normal working conditions: Emphasises that the data was collected during actual daily professional activities rather than in a controlled lab. • Reliable time measurements: Refers to the filtered data used for the analysis, which the authors acknowledge was difficult to extract from the software. • Translation-related tasks: Identifies the broader professional workflow—including project management, file engineering, and reviewing—which the researchers note were neglected in this specific study. | AG15: Linguistic challenges; Technical aspects; Working conditions; Ethical aspects | AH15: =+COUNTIFS('Coded Segments'!$C$2:$C$913,SLR_Covidence_Data_Extraction__66_files[[#This Row],[Study ID_1]],'Coded Segments'!$D$2:$D$913,SLR_Covidence_Data_Extraction__66_files[[#Headers],[Adoption (AD) > AD_High]]) -> 1 | AI15: =+COUNTIFS('Coded Segments'!$C$2:$C$913,SLR_Covidence_Data_Extraction__66_files[[#This Row],[Study ID_1]],'Coded Segments'!$D$2:$D$913,SLR_Covidence_Data_Extraction__66_files[[#Headers],[Adoption (AD) > AD_Moderate]]) -> 0 | AJ15: =+COUNTIFS('Coded Segments'!$C$2:$C$913,SLR_Covidence_Data_Extraction__66_files[[#This Row],[Study ID_1]],'Coded Segments'!$D$2:$D$913,SLR_Covidence_Data_Extraction__66_files[[#Headers],[Adoption (AD) > AD_Low]]) -> 0 | AK15: =+COUNTIFS('Coded Segments'!$C$2:$C$913,SLR_Covidence_Data_Extraction__66_files[[#This Row],[Study ID_1]],'Coded Segments'!$D$2:$D$913,SLR_Covidence_Data_Extraction__66_files[[#Headers],[Adoption (AD) > AD_None]]) -> 0 | AL15: =+COUNTIFS('Coded Segments'!$C$2:$C$913,SLR_Covidence_Data_Extraction__66_files[[#This Row],[Study ID_1]],'Coded Segments'!$D$2:$D$913,SLR_Covidence_Data_Extraction__66_files[[#Headers],[Attitude (ATT) > ATT_Negative]]) -> 1 | AM15: =+COUNTIFS('Coded Segments'!$C$2:$C$913,SLR_Covidence_Data_Extraction__66_files[[#This Row],[Study ID_1]],'Coded Segments'!$D$2:$D$913,SLR_Covidence_Data_Extraction__66_files[[#Headers],[Attitude (ATT) > ATT_Positive]]) -> 2 | AN15: =+COUNTIFS('Coded Segments'!$C$2:$C$913,SLR_Covidence_Data_Extraction__66_files[[#This Row],[Study ID_1]],'Coded Segments'!$D$2:$D$913,SLR_Covidence_Data_Extraction__66_files[[#Headers],[Ethical Concerns (EC) > EC_Bias]]) -> 0 | AO15: =+COUNTIFS('Coded Segments'!$C$2:$C$913,SLR_Covidence_Data_Extraction__66_files[[#This Row],[Study ID_1]],'Coded Segments'!$D$2:$D$913,SLR_Covidence_Data_Extraction__66_files[[#Headers],[Ethical Concerns (EC) > EC_Copyright]]) -> 0 | AP15: =+COUNTIFS('Coded Segments'!$C$2:$C$913,SLR_Covidence_Data_Extraction__66_files[[#This Row],[Study ID_1]],'Coded Segments'!$D$2:$D$913,SLR_Covidence_Data_Extraction__66_files[[#Headers],[Ethical Concerns (EC) > EC_Data safety & confidentiality]]) -> 0 | AQ15: =+COUNTIFS('Coded Segments'!$C$2:$C$913,SLR_Covidence_Data_Extraction__66_files[[#This Row],[Study ID_1]],'Coded Segments'!$D$2:$D$913,SLR_Covidence_Data_Extraction__66_files[[#Headers],[Ethical Concerns (EC) > EC_Environmental sustainability]]) -> 0 | AR15: =+COUNTIFS('Coded Segments'!$C$2:$C$913,SLR_Covidence_Data_Extraction__66_files[[#This Row],[Study ID_1]],'Coded Segments'!$D$2:$D$913,SLR_Covidence_Data_Extraction__66_files[[#Headers],[Ethical Concerns (EC) > EC_Payment]]) -> 0 | AS15: =+COUNTIFS('Coded Segments'!$C$2:$C$912,SLR_Covidence_Data_Extraction__66_files[[#This Row],[Study ID_1]],'Coded Segments'!$D$2:$D$912,SLR_Covidence_Data_Extraction__66_files[[#Headers],[Ethical Concerns (EC) > EC_Quality]]) -> 1 | AT15: =+COUNTIFS('Coded Segments'!$C$2:$C$913,SLR_Covidence_Data_Extraction__66_files[[#This Row],[Study ID_1]],'Coded Segments'!$D$2:$D$913,SLR_Covidence_Data_Extraction__66_files[[#Headers],[Ethical Concerns (EC) > EC_Translators’ role & status]]) -> 0 | AU15: =+COUNTIFS('Coded Segments'!$C$2:$C$913,SLR_Covidence_Data_Extraction__66_files[[#This Row],[Study ID_1]],'Coded Segments'!$D$2:$D$913,SLR_Covidence_Data_Extraction__66_files[[#Headers],[Ethical Concerns (EC) > EC_Other]]) -> 0 | AV15: =+COUNTIFS('Coded Segments'!$C$2:$C$913,SLR_Covidence_Data_Extraction__66_files[[#This Row],[Study ID_1]],'Coded Segments'!$D$2:$D$913,SLR_Covidence_Data_Extraction__66_files[[#Headers],[Literacy (LIT) > LIT_Generic]]) -> 0 | AW15: =+COUNTIFS('Coded Segments'!$C$2:$C$913,SLR_Covidence_Data_Extraction__66_files[[#This Row],[Study ID_1]],'Coded Segments'!$D$2:$D$913,SLR_Covidence_Data_Extraction__66_files[[#Headers],[Literacy (LIT) > LIT_None ]]) -> 0 | AX15: =+COUNTIFS('Coded Segments'!$C$2:$C$913,SLR_Covidence_Data_Extraction__66_files[[#This Row],[Study ID_1]],'Coded Segments'!$D$2:$D$913,SLR_Covidence_Data_Extraction__66_files[[#Headers],[Literacy (LIT) > LIT_Low ]]) -> 0 | AY15: =+COUNTIFS('Coded Segments'!$C$2:$C$913,SLR_Covidence_Data_Extraction__66_files[[#This Row],[Study ID_1]],'Coded Segments'!$D$2:$D$913,SLR_Covidence_Data_Extraction__66_files[[#Headers],[Literacy (LIT) > LIT_High]]) -> 0
A16: 22 | B16: BQX7YUQS | C16: Koponen 2020 | D16: MT for Subtitling: Investigating professional translators’ user experience and feedback | E16: Maarit Koponen E-mail: maarit.koponen@helsinki.fi | F16: Department of Digital Humanities, HELDIG, University of Helsinki, Finland | G16: Finland | H16: 2020/10 | I16: =LEFT(SLR_Covidence_Data_Extraction__66_files[[#This Row],[Publication date]],4) -> 2020 | J16: Finland | K16: To investigate the usability of machine translation (MT) and post-editing (PE) within the interlingual subtitling workflow, specifically from the perspective of the professional translators who use these tools. | L16: Questionnaire | N16: Interviews | O16: Other: Post-editing tasks | S16: 2019/11 | T16: 2020 | U16: Other: Professional translators from the Finnish public broadcasting company | V16: Online | W16: Offline | Y16: Professional subtitle translators | Z16: Professional translators | AA16: Audiovisual | AB16: 12 | AC16: 12 | AD16: 1. User Experience Questionnaire (UEQ) Results • Average Neutrality: On a scale of -3 to +3, the average scores for most adjective pairs fell within the neutral range (-0.8 to +0.8). • Negative Outliers: The most negative reactions from participants described the process as "labourious" and "limiting" regarding their creativity. • The Model Paradox: While automatic evaluation metrics (BLEU) indicated that document-level models were superior, translators in the manual assessment showed a slight preference for sentence-level output or saw no significant difference between the two. 2. The Critical Role of Spotting and Segmentation The most significant barrier to a positive user experience was not the quality of the translation itself, but how the text was timed and divided on the screen: • Poor Assessment: Automatic spotting (timing) and segmentation (how sentences are split into subtitle frames) were generally assessed as poor, particularly in the document-level models. • Interview Feedback: All 12 participants commented negatively on these issues, noting that subtitles were frequently out of sync with the audio or that sentences were incorrectly split across frames. • Impact on Effort: Participants noted that fixing off-sync subtitles often led them to make unnecessary linguistic changes, increasing their overall cognitive load. 3. Language Pair and Quality Variations The results varied significantly depending on the language direction: • English→Finnish: These translators were the most critical, evaluating nearly all aspects of the process negatively. • Finnish→English: This group provided the most positive feedback, reaching positive averages for categories like "efficiency" and "ease of use". • Quality Mentions: In interviews, translators made 30 negative mentions regarding MT quality (lexical errors, ungrammatical structures) but also 23 positive mentions, specifically praising the MT for providing useful terminology. 4. Productivity and Workflow Impact • Efficiency Paradox: On average, MTPE was "slightly faster" than translating from scratch. However, 5 out of the 12 participants were actually slower when post-editing. • Sentimental Divide: 55% of all statements made in interviews were negative. Many translators felt MTPE involved more effort than traditional translation and worried it could lead to a lower quality final product. • Future Adoption: Only four participants said they would definitely consider using MT in their work; six were mixed, and two rejected the idea entirely. | AE16: 1. The Dominance of Technical Constraints The researchers concluded that the quality of the translation output is secondary to the technical challenges of spotting and segmentation. • The Segmentation Gap: Even when automatic metrics (like BLEU) showed that sophisticated document-level models were superior, translators found them harder to use because the timing and frame divisions were often poor. • Forced Errors: Misaligned or off-sync subtitles were identified as a "major issue" that increased cognitive load, sometimes forcing translators to make unnecessary linguistic changes just to fit the technical constraints. 2. Emotional and Creative Impact A key conclusion is that the experience of post-editing is often perceived as psychologically restrictive. • Creative Limitation: Translators described the process as "limiting" and "annoying", expressing feelings of being "trapped by MT". • Comparison to Literature: As seen in our conversation history with the Ruffo (2018) and Ruokonen and Salmi (2024) studies, this research confirms that even in highly technical fields like subtitling, professionals fear that automation "threatens the essence" and creativity of their work. 3. The Productivity Paradox The study concluded that MTPE does not offer a guaranteed productivity boost. • Inconsistent Gains: While MTPE was "slightly faster" on average, nearly half (5 out of 12) of the participants were actually slower when post-editing than when translating from scratch. • Increased Effort: Many participants felt the process involved more effort than traditional translation, leading to a largely neutral-to-negative overall impression. 4. Language Pair Sensitivity The researchers found that the success of MTPE is highly dependent on the language direction. • English→Finnish translators were the most critical, evaluating nearly all aspects of the process negatively. • Conversely, Finnish→English translators were the most positive, suggesting that MTPE may be more viable for certain linguistic combinations than others. 5. Future Outlook and Openness Despite the technical frustrations, the study concluded that professional translators are not entirely "anti-technology". • Conditional Adoption: Most participants (10 out of 12) were either open to using MT for specific content or were mixed/undecided. • Terminology Support: Similar to the Prieto Ramos (2025) study in our history, translators identified terminology aid as the most valuable potential use for MT in their workflow. • Need for Better Tools: The final conclusion emphasizes that current subtitling software is not designed for MTPE, and future success depends on better integration and improved automatic segmentation. | AF16: • User evaluation: Refers to the overall assessment methodology used to study the professional translators' interactions with the technology. • MTPE (Machine Translation Post-Editing): The core process being investigated, specifically for subtitle translation. • User experience questionnaire: One of the primary data collection tools used to measure the translators' subjective impressions. • Thematic analysis of interviews: The qualitative method used to extract deeper insights from the participants' detailed verbal feedback. • Limiting and somewhat annoying: These are the specific characterisations used by the translators to describe their experience of the post-editing process. • Segmentation and timing: Identified as the "major issues" that negatively impacted the workflow, alongside overall MT quality. • Applicability of MTPE: Used in the context of the study's goal to determine if and how post-editing can be effectively integrated into professional subtitling. | AG16: Linguistic challenges; Technical aspects; Ethical aspects | AH16: =+COUNTIFS('Coded Segments'!$C$2:$C$913,SLR_Covidence_Data_Extraction__66_files[[#This Row],[Study ID_1]],'Coded Segments'!$D$2:$D$913,SLR_Covidence_Data_Extraction__66_files[[#Headers],[Adoption (AD) > AD_High]]) -> 1 | AI16: =+COUNTIFS('Coded Segments'!$C$2:$C$913,SLR_Covidence_Data_Extraction__66_files[[#This Row],[Study ID_1]],'Coded Segments'!$D$2:$D$913,SLR_Covidence_Data_Extraction__66_files[[#Headers],[Adoption (AD) > AD_Moderate]]) -> 0 | AJ16: =+COUNTIFS('Coded Segments'!$C$2:$C$913,SLR_Covidence_Data_Extraction__66_files[[#This Row],[Study ID_1]],'Coded Segments'!$D$2:$D$913,SLR_Covidence_Data_Extraction__66_files[[#Headers],[Adoption (AD) > AD_Low]]) -> 0 | AK16: =+COUNTIFS('Coded Segments'!$C$2:$C$913,SLR_Covidence_Data_Extraction__66_files[[#This Row],[Study ID_1]],'Coded Segments'!$D$2:$D$913,SLR_Covidence_Data_Extraction__66_files[[#Headers],[Adoption (AD) > AD_None]]) -> 0 | AL16: =+COUNTIFS('Coded Segments'!$C$2:$C$913,SLR_Covidence_Data_Extraction__66_files[[#This Row],[Study ID_1]],'Coded Segments'!$D$2:$D$913,SLR_Covidence_Data_Extraction__66_files[[#Headers],[Attitude (ATT) > ATT_Negative]]) -> 6 | AM16: =+COUNTIFS('Coded Segments'!$C$2:$C$913,SLR_Covidence_Data_Extraction__66_files[[#This Row],[Study ID_1]],'Coded Segments'!$D$2:$D$913,SLR_Covidence_Data_Extraction__66_files[[#Headers],[Attitude (ATT) > ATT_Positive]]) -> 1 | AN16: =+COUNTIFS('Coded Segments'!$C$2:$C$913,SLR_Covidence_Data_Extraction__66_files[[#This Row],[Study ID_1]],'Coded Segments'!$D$2:$D$913,SLR_Covidence_Data_Extraction__66_files[[#Headers],[Ethical Concerns (EC) > EC_Bias]]) -> 0 | AO16: =+COUNTIFS('Coded Segments'!$C$2:$C$913,SLR_Covidence_Data_Extraction__66_files[[#This Row],[Study ID_1]],'Coded Segments'!$D$2:$D$913,SLR_Covidence_Data_Extraction__66_files[[#Headers],[Ethical Concerns (EC) > EC_Copyright]]) -> 0 | AP16: =+COUNTIFS('Coded Segments'!$C$2:$C$913,SLR_Covidence_Data_Extraction__66_files[[#This Row],[Study ID_1]],'Coded Segments'!$D$2:$D$913,SLR_Covidence_Data_Extraction__66_files[[#Headers],[Ethical Concerns (EC) > EC_Data safety & confidentiality]]) -> 0 | AQ16: =+COUNTIFS('Coded Segments'!$C$2:$C$913,SLR_Covidence_Data_Extraction__66_files[[#This Row],[Study ID_1]],'Coded Segments'!$D$2:$D$913,SLR_Covidence_Data_Extraction__66_files[[#Headers],[Ethical Concerns (EC) > EC_Environmental sustainability]]) -> 0 | AR16: =+COUNTIFS('Coded Segments'!$C$2:$C$913,SLR_Covidence_Data_Extraction__66_files[[#This Row],[Study ID_1]],'Coded Segments'!$D$2:$D$913,SLR_Covidence_Data_Extraction__66_files[[#Headers],[Ethical Concerns (EC) > EC_Payment]]) -> 0 | AS16: =+COUNTIFS('Coded Segments'!$C$2:$C$912,SLR_Covidence_Data_Extraction__66_files[[#This Row],[Study ID_1]],'Coded Segments'!$D$2:$D$912,SLR_Covidence_Data_Extraction__66_files[[#Headers],[Ethical Concerns (EC) > EC_Quality]]) -> 6 | AT16: =+COUNTIFS('Coded Segments'!$C$2:$C$913,SLR_Covidence_Data_Extraction__66_files[[#This Row],[Study ID_1]],'Coded Segments'!$D$2:$D$913,SLR_Covidence_Data_Extraction__66_files[[#Headers],[Ethical Concerns (EC) > EC_Translators’ role & status]]) -> 0 | AU16: =+COUNTIFS('Coded Segments'!$C$2:$C$913,SLR_Covidence_Data_Extraction__66_files[[#This Row],[Study ID_1]],'Coded Segments'!$D$2:$D$913,SLR_Covidence_Data_Extraction__66_files[[#Headers],[Ethical Concerns (EC) > EC_Other]]) -> 0 | AV16: =+COUNTIFS('Coded Segments'!$C$2:$C$913,SLR_Covidence_Data_Extraction__66_files[[#This Row],[Study ID_1]],'Coded Segments'!$D$2:$D$913,SLR_Covidence_Data_Extraction__66_files[[#Headers],[Literacy (LIT) > LIT_Generic]]) -> 0 | AW16: =+COUNTIFS('Coded Segments'!$C$2:$C$913,SLR_Covidence_Data_Extraction__66_files[[#This Row],[Study ID_1]],'Coded Segments'!$D$2:$D$913,SLR_Covidence_Data_Extraction__66_files[[#Headers],[Literacy (LIT) > LIT_None ]]) -> 0 | AX16: =+COUNTIFS('Coded Segments'!$C$2:$C$913,SLR_Covidence_Data_Extraction__66_files[[#This Row],[Study ID_1]],'Coded Segments'!$D$2:$D$913,SLR_Covidence_Data_Extraction__66_files[[#Headers],[Literacy (LIT) > LIT_Low ]]) -> 0 | AY16: =+COUNTIFS('Coded Segments'!$C$2:$C$913,SLR_Covidence_Data_Extraction__66_files[[#This Row],[Study ID_1]],'Coded Segments'!$D$2:$D$913,SLR_Covidence_Data_Extraction__66_files[[#Headers],[Literacy (LIT) > LIT_High]]) -> 0
A17: 17 | B17: EFPQLTVX | C17: Moorkens 2020 | D17: Comparative satisfaction among freelance and directly-employed Irish-language translators | E17: Joss Moorkens E-mail: joss.moorkens@dcu.ie | F17: Dublin City University, Ireland | G17: Ireland | H17: 2020/02/25 | I17: =LEFT(SLR_Covidence_Data_Extraction__66_files[[#This Row],[Publication date]],4) -> 2020 | J17: Ireland | K17: To investigate and compare job satisfaction among government-accredited Irish-language translators working under different employment models | L17: Questionnaire | S17: 2016/08/09 | T17: 2016/09/01 | U17: Professional associations networks | V17: Online | X17: This work was supported by the ADAPT SFI Research Centre at Dublin City University and the Department of Culture, Heritage and the Gaeltacht. ADAPT is funded by Science Foundation Ireland through the SFI Research Centres Programme and co-funded under the European Regional Development Fund (ERDF) through Grant 13/RC/2106. | Y17: Accredited Irish language translators | Z17: Professional translators | AA17: General | AB17: 178 | AC17: 178 | AD17: 1. Universal Pride vs. Employment Disparity • Strong Sense of Pride: All translators, regardless of their employment model, reported a strong sense of pride in their work (averaging 4.21 on a 5-point scale). They also generally enjoy the task of translation. • The Satisfaction Gap: Freelance translators scored significantly lower than public servants in key satisfaction areas. For instance, public servants reported a higher sense of work purpose (4.25) compared to freelancers (3.68). • Fairness and Pay: A significant difference was found regarding the perceived fairness of payment and procedures, where public servants and company employees averaged a score of 4.0, while freelancers averaged only 3.07. 2. Job Security and Professional Isolation • Security Contrast: Public servants feel very secure in their roles (1.75 on a scale of "no security"), whereas freelancers feel much more precarious (3.18). • Isolation: The study found a general tendency for translators to feel isolated at work (averaging 2.71). For some freelancers, this isolation was described as "literally killing me" and was a primary reason for considering leaving the profession. 3. Major Professional Threats: The "Race to the Bottom" • Top Concerns: When asked about the main threats to the profession, the most cited issues were falling quality (27 responses), low rates (23 responses), and Machine Translation (MT) (11 responses). • Price Pressure: Participants described a "race to the bottom" where agencies aggressively lower rates, sometimes as low as €0.05 per word, leading to a situation where price is prioritised over precision and experience. • Unqualified Competition: Translators expressed frustration with a "shortage of good Irish translators," which often results in assignments being poorly performed by unqualified individuals. 4. Divergent Attitudes Toward Technology • MT and Post-Editing: Attitudes toward MT were mixed, with 22 negative comments versus 15 positive ones. Freelance translators generally feel threatened by technology and expressed "powerlessness" regarding their translations being used to train MT engines. • Public Service View: In contrast, public service translators were more well-disposed toward technology, viewing MT as a tool to help handle the large volumes of work required by the end of the EU derogation. • Creative Freedom: Interestingly, freelance work was seen as offering a greater opportunity to be creative (3.48) compared to work in the public service (2.88). 5. The Irish Language Policy Context • Domestic vs. EU Policy: Respondents were largely negative about domestic Irish language policy, with many feeling that the requirement to translate reports "that nobody ever reads" was unhelpful. • EU Benefits: Conversely, all 52 respondents agreed that the EU is beneficial for the Irish language, viewing it as a path toward the "normalisation" of the language in a modern setting. • Technological Optimism: Most participants (all but two) were positive about the effects of social media and technology on the visibility and revival of the Irish language outside of traditional Gaeltacht areas. | AE17: 1. A Tiered Employment Market The study concludes that there is a tiered employment market in translation based on working conditions. • Freelance Vulnerability: Freelance participants’ perceptions of purpose, fairness, payment, and job security compare poorly to their full-time public service colleagues. • Shared Pride: Despite these disparities, all translators, regardless of employment status, maintain a strong sense of pride in their work. 2. Technological Polarisation Attitudes toward technology are sharply divided along employment lines: • Public Service Optimism: These translators are generally well-disposed toward technology and the need for upskilling, viewing Machine Translation (MT) as a tool to leverage the small pool of accredited translators to meet high institutional demand. • Freelance Anxiety: Freelance translators often feel threatened by technology, fearing that MT will replace human translators and expressing "powerlessness" over their work being used without permission to train MT engines. 3. Socio-Economic Threats to Sustainability The researchers conclude that several factors are undermining the long-term sustainability of the profession: • "Race to the Bottom": Freelancers are struggling with falling rates and an inability to negotiate collectively, leading some to accept low-paying jobs that damage the interests of the entire professional community. • Quality and Talent Gaps: There is a pervasive fear of dropping translation quality and a "brain drain," where the best translation talent may move to Europe, leaving a shortage of high-level skills domestically. • Attracting New Entrants: If the profession becomes too unappealing due to low morale, isolation, and poor compensation, it may fail to attract the new entrants needed to meet upcoming legal requirements for Irish translation. 4. Shifting Linguistic Context The study concludes that the Irish language is in a state of transition; while it is declining in traditional Gaeltacht areas, it is experiencing a digital-age revival through social media and the "e-gaeltacht" among the urban middle class. | AF17: • Minority-language translators: Describes the specific cohort of the study, noting the unique linguistic and political context of the Irish language. • Employment models: Refers to the different categories of participants, including freelance, self-employed, public service, and directly-employed translators. • Perceptions of purpose and fairness: Identifies the key satisfaction metrics—work purpose, fair payment, and procedural fairness—where freelance results compared poorly to public service results. • Pride in work: A term used to describe a universal sentiment found across all categories of translators, regardless of their employment status. • Falling rates: Highlights the economic pressure on freelancers, who report that pay is lower than in previous years and continues to drop. • Politically legitimated human values: A concept used to argue that technical work like translation should be oriented toward human value rather than the "whims of profit-making organisations". • Upskilling: Describes the requirement for public service translators to continually update their skills to handle technological advancements. • Dilution of language variety and quality: A specific fear expressed regarding the use of Machine Translation (MT), which could lead to standardised and less rich linguistic output. • Powerlessness: Used to characterise the feelings of freelance translators regarding their human translations being repurposed for MT training without their control. • Lack of translation talent: Refers to the concern that there are not enough highly skilled individuals to meet the growing institutional demand for Irish translation. • Lack of an audience: Notes the fear that much of the translated material may not actually be read by the public. • Gaeltacht areas vs. Urban middle class: Describes the shifting demographics of the language, noting the ongoing decline of traditional Irish-speaking regions in contrast to growth among urban populations. • 'e-gaeltacht' and Social media: Terms used to describe the digital revival and new visibility of the Irish language in the modern setting. | AG17: Linguistic challenges; Technical aspects; Training needs; Working conditions; Ethical aspects | AH17: =+COUNTIFS('Coded Segments'!$C$2:$C$913,SLR_Covidence_Data_Extraction__66_files[[#This Row],[Study ID_1]],'Coded Segments'!$D$2:$D$913,SLR_Covidence_Data_Extraction__66_files[[#Headers],[Adoption (AD) > AD_High]]) -> 0 | AI17: =+COUNTIFS('Coded Segments'!$C$2:$C$913,SLR_Covidence_Data_Extraction__66_files[[#This Row],[Study ID_1]],'Coded Segments'!$D$2:$D$913,SLR_Covidence_Data_Extraction__66_files[[#Headers],[Adoption (AD) > AD_Moderate]]) -> 0 | AJ17: =+COUNTIFS('Coded Segments'!$C$2:$C$913,SLR_Covidence_Data_Extraction__66_files[[#This Row],[Study ID_1]],'Coded Segments'!$D$2:$D$913,SLR_Covidence_Data_Extraction__66_files[[#Headers],[Adoption (AD) > AD_Low]]) -> 0 | AK17: =+COUNTIFS('Coded Segments'!$C$2:$C$913,SLR_Covidence_Data_Extraction__66_files[[#This Row],[Study ID_1]],'Coded Segments'!$D$2:$D$913,SLR_Covidence_Data_Extraction__66_files[[#Headers],[Adoption (AD) > AD_None]]) -> 0 | AL17: =+COUNTIFS('Coded Segments'!$C$2:$C$913,SLR_Covidence_Data_Extraction__66_files[[#This Row],[Study ID_1]],'Coded Segments'!$D$2:$D$913,SLR_Covidence_Data_Extraction__66_files[[#Headers],[Attitude (ATT) > ATT_Negative]]) -> 3 | AM17: =+COUNTIFS('Coded Segments'!$C$2:$C$913,SLR_Covidence_Data_Extraction__66_files[[#This Row],[Study ID_1]],'Coded Segments'!$D$2:$D$913,SLR_Covidence_Data_Extraction__66_files[[#Headers],[Attitude (ATT) > ATT_Positive]]) -> 2 | AN17: =+COUNTIFS('Coded Segments'!$C$2:$C$913,SLR_Covidence_Data_Extraction__66_files[[#This Row],[Study ID_1]],'Coded Segments'!$D$2:$D$913,SLR_Covidence_Data_Extraction__66_files[[#Headers],[Ethical Concerns (EC) > EC_Bias]]) -> 0 | AO17: =+COUNTIFS('Coded Segments'!$C$2:$C$913,SLR_Covidence_Data_Extraction__66_files[[#This Row],[Study ID_1]],'Coded Segments'!$D$2:$D$913,SLR_Covidence_Data_Extraction__66_files[[#Headers],[Ethical Concerns (EC) > EC_Copyright]]) -> 1 | AP17: =+COUNTIFS('Coded Segments'!$C$2:$C$913,SLR_Covidence_Data_Extraction__66_files[[#This Row],[Study ID_1]],'Coded Segments'!$D$2:$D$913,SLR_Covidence_Data_Extraction__66_files[[#Headers],[Ethical Concerns (EC) > EC_Data safety & confidentiality]]) -> 0 | AQ17: =+COUNTIFS('Coded Segments'!$C$2:$C$913,SLR_Covidence_Data_Extraction__66_files[[#This Row],[Study ID_1]],'Coded Segments'!$D$2:$D$913,SLR_Covidence_Data_Extraction__66_files[[#Headers],[Ethical Concerns (EC) > EC_Environmental sustainability]]) -> 0 | AR17: =+COUNTIFS('Coded Segments'!$C$2:$C$913,SLR_Covidence_Data_Extraction__66_files[[#This Row],[Study ID_1]],'Coded Segments'!$D$2:$D$913,SLR_Covidence_Data_Extraction__66_files[[#Headers],[Ethical Concerns (EC) > EC_Payment]]) -> 1 | AS17: =+COUNTIFS('Coded Segments'!$C$2:$C$912,SLR_Covidence_Data_Extraction__66_files[[#This Row],[Study ID_1]],'Coded Segments'!$D$2:$D$912,SLR_Covidence_Data_Extraction__66_files[[#Headers],[Ethical Concerns (EC) > EC_Quality]]) -> 2 | AT17: =+COUNTIFS('Coded Segments'!$C$2:$C$913,SLR_Covidence_Data_Extraction__66_files[[#This Row],[Study ID_1]],'Coded Segments'!$D$2:$D$913,SLR_Covidence_Data_Extraction__66_files[[#Headers],[Ethical Concerns (EC) > EC_Translators’ role & status]]) -> 2 | AU17: =+COUNTIFS('Coded Segments'!$C$2:$C$913,SLR_Covidence_Data_Extraction__66_files[[#This Row],[Study ID_1]],'Coded Segments'!$D$2:$D$913,SLR_Covidence_Data_Extraction__66_files[[#Headers],[Ethical Concerns (EC) > EC_Other]]) -> 0 | AV17: =+COUNTIFS('Coded Segments'!$C$2:$C$913,SLR_Covidence_Data_Extraction__66_files[[#This Row],[Study ID_1]],'Coded Segments'!$D$2:$D$913,SLR_Covidence_Data_Extraction__66_files[[#Headers],[Literacy (LIT) > LIT_Generic]]) -> 0 | AW17: =+COUNTIFS('Coded Segments'!$C$2:$C$913,SLR_Covidence_Data_Extraction__66_files[[#This Row],[Study ID_1]],'Coded Segments'!$D$2:$D$913,SLR_Covidence_Data_Extraction__66_files[[#Headers],[Literacy (LIT) > LIT_None ]]) -> 0 | AX17: =+COUNTIFS('Coded Segments'!$C$2:$C$913,SLR_Covidence_Data_Extraction__66_files[[#This Row],[Study ID_1]],'Coded Segments'!$D$2:$D$913,SLR_Covidence_Data_Extraction__66_files[[#Headers],[Literacy (LIT) > LIT_Low ]]) -> 0 | AY17: =+COUNTIFS('Coded Segments'!$C$2:$C$913,SLR_Covidence_Data_Extraction__66_files[[#This Row],[Study ID_1]],'Coded Segments'!$D$2:$D$913,SLR_Covidence_Data_Extraction__66_files[[#Headers],[Literacy (LIT) > LIT_High]]) -> 0
